Workbook

Sheet HUCs Ordinances
A1: Ordinance Number | B1: Ordinance Description | C1: Full Text | D1: City | E1: E-Governance Index | F1: Overall CMCI Score
A2: AS OF 04-11-2024 | B2: PROPOSED AMENDMENTS "AN ORDINANCE ADOPTING THE REVISED PASAY CITY REVENUE CODE" | C2: Republic of the Philippines SANGGUNIANG PANLUNGSOD Pasay City Ordinance No.______, Series of 2024 AN ORDINANCE ADOPTING THE REVISED PASAY CITY REVENUE CODE Introduced by: Vice Mayor Waldetrudes S . Del Rosario Sponsored by: Councilor Mary Grace B. Santos Co-Sponsored by: Counci lors Mark Anthony A. Calixto, Marlon A. Pesebre, Ma. Antonia C. Cuneta, Abraham Albert Q. Alvina, Ricardo E. Santos, Jose C. Isidro, Jr., Editha Y. Manguerra, Donnabel M. Vendivel, Jennifer D. Panaligan, King Marlon A. Magat, Angelo Nicol P. Arceo, Julie G. Gonzales and Jose Miguel A. Mañez WHEREAS , Section 5, Article X of the 1987 Constitution provides that each local government unit shall have the power to create its own sources of revenues and to levy taxes, fees, and charges subject to such guidelines and limitations as the Congress may provide, consistent with the basic policy of local autonomy. Such taxes, fees, and charges shall accrue exclusively to the local governments ; WHEREAS , Section 129, Republic Act No. 7160, otherwise known as the Local Government Code of 1991, provinces, cities, and municipalities have the power to generate their sources of revenue. These local sources consist of: (a) tax revenues derived from real property tax, business tax, and other taxes; and (b) non- tax revenues derived from fees, charges, and receipts from the operation of economic enterprises in connection with the government’s exercise of its proprietary functions; WHEREAS , the main thrust of the C ity Government is for urban growth and progressive redistribution of wealth. It calls for a rational, more profitable , and fruitful endeavor to attain self- reliance, a consistent and practical delivery of services, the enforcement and effective prosecution of social, environmental , and economic development projects; WHEREAS , to ensure the maintenance, completion, promotion, and operation of the socio- economic development projects initiated by the C ity G overnment, it is highly imperative to maximize revenue collections of the C ity and its integrated development machinery; WHEREAS, to attain this objective, without unduly disturbing the initiative and growth of business, trade , and industry, the need for coordinating into one effective code all the revenue resources in the City Government becomes imperative; WHEREAS , on 15 November 1993, the City Council approved the latest revenue code of Pasay City with Ordinance No. 241 Series of 1993 entitled “An Ordinance Adopting the Pasay City Revenue Code .” WHEREAS , due to the ever -changing needs of the City and the continuous transformation of society, it is proper to update and revise the revenue code. NOW THEREFORE, BE IT ORDAINED as it is hereby ORDAINED by the Sangguniang Panlungsod in a session duly assembled: TITLE I. CHAPTER 1 GENERAL PROVISIONS Section 1. Title. – This City Ordinance shall be known as the “ 2024 Revised Pasay City Revenue Code”. Section 2. Scope. – This Code governs the administration, appraisal, assessment, levy, and collection of taxes, fees and charges in the City of Pasay. Section 3. Legal Basis. – This Code is enacted in accordance with the provisions of Republic Act 7160, otherwise known as the Local Government Code of 1991. Section 4. Fundamental Principles. – The following fundamental princip les govern the exercise of the C ity government's power of taxation and other revenue- raising powers: Page 2 of 137 Ordinance No. ______, Series 202 4 AN ORDINANCE ADOPTING THE 2024 REVISED PASAY CITY REVENUE CODE x------------------------------------x a) Taxation shall be uniform in each local government unit ; b) Taxes, fees, charges , and other impositions shall: 1. Be equitable and based as far as practicable on the taxpayer's ability to pay ; 2. Be levied and collected only for public purposes ; 3. Not be unjust, excessive, oppressive, or confiscatory ; 4. Not be contrary to law, public policy, national, economic policy or in restraint of trade. c) The collection of these local taxes, fees, charges, and other impositions shall in no case be let to any private persons; d) The revenue collected pursuant to the provisions of this Code shall inure solely to the benefit of, and subject to disposition by the City government, unless otherwise specifically provided in the Local Government Code; e) The C ity government shall evolve a progressive system of taxation. Section 5. Rules of Construction. – In constructing any provisions of this Code, the following rules of construction shall be observed unless inconsistent with the manifest intent of such provision. a) Words and Phrases – words and phrases shall be understood according to their common and approved usage. Words and phrases which may require a technical, peculiar , or appropriate meaning under this Code shall be constructed and understood according to such technical, peculiar, or appropriate meaning. b) Gender and Number – every word in this Code importing the masculine gender shall extend and apply to both males and females . Every word importing th e singular number shall extend and apply to one person or thing as well. Every word importing the plural number shall extend and apply to several persons or things as swell. c) Reasonable Time – in all cases where an action is required to be done within a reasonable time, the time shall be deemed to mean such period as may be necessary for the prompt performance of the act. d) Computation of Time – the time within which an act is to be done as provided in this Code or in any rule or regulation issued pursuant thereto when expressed in days shall be computed by excluding the first day and including the last day. If the last day falls on Sunday or a holiday, the same shall be excluded from the computation , and the day following shall be the last day. e) Conflicting Provisions of Sections – if the provisions of different sections in the same chapter conflict with each other, the provision of the sections which is last in point or sequence shall prevail. Section 6. Definition of Terms. – When used in this Code, the term: “Acquisition Cost ” for newly acquired machinery not yet depreciated and appraised within the year of its purchase, refers to the actual cost of the machinery to its present owner plus the cost of transportation handling and installation at the present site; “Actual Use ” refers to the purpose for which the property is principally or predominantly utilized by the person in possession thereof; “Ad Valorem Tax ” is a levy on real property determined on the basis of a fixed proportion of the value of the property; "Agricultural Products " includes the yield of the soil such as: corn, rice, wheat, rye, hay, coconuts, sugarcanes, tobaccos, root crops, vegetables, fruits, flowers and its by-products; ordinary salt; all kinds of fish; poultry; and livestock and animal products, whether in their original form or not. The phrase "whether in their original form or not" refers to the transformation of said products by the farmer, fisherman, produce r or owner through the application of processes to preserve or otherwise to pre pare said products for the market such as freezing, dyeing, salting, smoking, or stripping for purposes of preserving or otherwise preparing said products for the market. Page 3 of 137 Ordinance No. ______, Series 202 4 AN ORDINANCE ADOPTING THE 2024 REVISED PASAY CITY REVENUE CODE x------------------------------------x "Amusement " is a pleasurable diversion and entertainment. It is synonymous to relaxation, avocation, pastime, or fun; "Amusement Places " include theaters, cinemas, concert halls, and other places of amusement where one seeks admission to entertain oneself by seeing or viewing the show or performances; ''Business" means trade or commercial activity regularly engaged in as means of livelihood or with a view to profit; "Banks and Other Financial Institution" include non- bank financial intermediaries, lending investors, finance and companies, stock markets, stock brokers , and dealers in securities and foreign exchange, as defined under applicable laws or rules and regulations there under;s "Capital Investment " is the capital that the person employs in any undertaking or which he contributes to the capital of a partnership, corporation, or any other juridical entity or association in a particular taxing jurisdiction; "Charges " refer to pecuniary liability, as rents or fees against person s or property; “Contractor " includes persons, natural or juridical, not subject to professional tax under Section 1 01 of this Code, whose activity consists essentially of the sale of all kinds of services for a fee, regardless of whether or not the performance of the service calls for the exercise or use of the physical or mental faculties of such contractor or his employees. The term " contractor " shall include general engineering, general building and especially contractors as defined under applicable laws; filling, demolition and salvage works contractors; proprietors or operators of mine drilling apparatus; proprietors or operators of dockyards; persons engaged in the installation of water systems, and gas or electric light, heat, or power; proprietors or operators of smelting plants, engraving, plating, and plastic lamination establishments proprietors or operators of establ ishments for repairing, repainting, upholstering, washing or greasing of vehicles, heavy equipment, vulcanizing, recapping and battery charging; proprietors or operators of furniture shops and establishments of planning or surfacing and re- cutting of lumber, and sawmills under contract to saw or cut logs belonging to others; proprietor or operators of dry cleaning or dyeing establishments, steam laundries, and laundries using washing machines; proprietors or owners of shop for the repair of any kind of mechanical and electrical devices, instruments, apparatus, or furniture and shoe repairing by machine or any mechanical contrivance; proprietors or operators of establishments or lots for parking purposes; proprietors or operators of tailor shops, dress shops, milliners and hatters, beauty parlors, barber shops, massage clinics, sauna, Turkish and Swedish baths, slenderizing and building saloons, and similar establishments; photographic studios; funeral parlors; proprietors or operators of hotels, motels, and l odging houses; proprietors or operators of arrastre and stevedoring, warehousing or forwarding establishment s; master plumbers, smiths, and house and sign painters; printers, bookbinders, lightgraphers; publisher except those engaged in the publication and printing of any newspapers, magazine, review or bulletin which appears at regular intervals with fixed prices for subscription and sale and which is not devote d principally to the publication of advertisement; business agents, private detective or watchman agencies, commercial and immigration brokers, and cinematographic film owners, lessors and distributors. “Appraisal ” is the act or process of determining the value of property as of a specific date for a specific purpose; “Assessed Value ” is the fair market value of the real property multiplied by the assessment level. It is synonymous with taxable value; “Assessment ” is the act or process of determining the value of a property, or proportion thereof subject to tax, including the discovery, listing, classification, and appraisal of properties; “Assessment Level ” is the percentage applied to the fair market value to determine the taxable value of the property; “Commercial Land ” is land devoted principally to the object of profit and is not classified as agricultural, industrial, mineral, timber, or residential land . “Corporation” includes partnership, no matter how created or organized, joint-stock companies, joint accounts, associations , or insurance companies but does not include general professional partnerships and a joint venture Page 4 of 137 Ordinance No. ______, Series 202 4 AN ORDINANCE ADOPTING THE 2024 REVISED PASAY CITY REVENUE CODE x------------------------------------x or consortium formed to undertake construction projects or engage in petroleum, coal, geothermal, and other energy operations under an operating or consortium agreement under a service contract with the government. General professional partnerships are partnerships formed by the person for the sole purpose of exercising their common profession, no part of the income of which is derived from engaging in any trade or business; “Countryside and Barangay Business Enterprise " refers to any business entity, association, or cooperative registered under the provisions of Republic Act No. 6810, otherwise known as "Magna Carta for Countryside and Barangay Business Enterprise (Kalakalan20)"; "Dealer " means one whose business is to buy and sell merchandise, goods, and chattels as a merchant. He stands immediately between the producer or manufacturer and the consumer and depends for his profit not upon the labor he bestows upon his commodities but upon the skill and foresight with which he watches the market; “Depreciated Value ” is the value remaining after deducting depreciation from the acquisition cost; “Economic Life ” is the estimated period over which it is anticipated that machinery or equipment may be profitably utilized; “Fair Market Value ” is the price at which a property may be sold by a seller who is not compelled to sell and bought by a buyer who is not compelled to buy; "Fee" means a charge fixed by law or ordinance for the regulation or inspection of a business or activity. "Franchise " is a right or privilege, affected by the public interest which is conferred upon private persons or corporations, under such terms and conditions as the government and its political subdivisions may impose in the interest of public welfare, security, and safety; "Gross Sales or Receipts" include the total amount of the money or its equivalent representing the contract price, compensation, or service fee, including the amount charged or materials supplied with the services and deposits or advance payments actually or constructively received during the taxable quarte r for the services performed or to be performed for another person excluding discounts if determinable at the time of sales, sales return, excise tax, and value- added tax (VAT); “Manufacturing" includes every person who, by physical or chemical process, alters the exterior texture or form or inner substance of any raw material or manufactured or partially manufactured product in such manner as to prepare it for special use or uses to which it could have not been put in its original condition, or who by any such process, combines any such raw material or manufactured or partially manufactured products with other materials or products of the same or of different kinds and in such manner that the finished products of such process or manufacture can be put to a special use or uses to which such raw materials or manufactured or partially manufactured products in their original condition could have not been put, and who in addition, alter s such raw material or manufactured or partially manufactured products, or combines the same to produce such finished products for the purpose of their sale or distribution to others and not for his own use or consumption; “Improvement ” is a valuable addition made to a property or an amelioration in its condition, amounting to more than a mere repair or replacement of parts involving capital expenditures and labor which is intended to enhance its value, beauty or utility or to adopt it for new or other purposes; “Industrial Land” is land devoted principally to industrial activity as capital investment and is not classified as agricultural, commercial, timber, mineral, or residential land; “Machinery ” embraces machines, equipment, mechanical contrivances, instruments, appliances or apparatus which may not be attached, permanently or temporarily to the real property. It includes the physical facilities for production, the installations and appurtenant service facilities, those which are mobile, self -powered or self- propelled, and those not permanently attached to the real property which are actually, directly and exclusively used to meet the needs of the particular industry, business or activity and which their very nature and purpose are designed for, or necessary to its manufacturing, mining, logging, commercial, industrial or agricultural purposes; "Marginal Farmer or Fisherman” refers to an individual engaged in subsistence farming or fishing which shall be limited to the sale , barter or exchange of agricultural or marine products produced by himself and his immediate family; Page 5 of 137 Ordinance No. ______, Series 202 4 AN ORDINANCE ADOPTING THE 2024 REVISED PASAY CITY REVENUE CODE x------------------------------------x "Motor Vehicle " means ·any vehicle propelled by any power other than muscular power using the public roads, but excluding road rollers, trolley cars, street -sweepers, sprinklers, lawn mowers, bulldozers, graders, forklifts, amphibian trucks, and cranes if not used on public roads, vehicles which run only on rails or tracks, and tractors, trailers and traction engines of all kinds use delusively for agriculture purposes; "Municipal Waters " include not only streams, lakes and tidal waters within the municipality, not being the subject of private ownership and not comprised within the national parks, public forest, timber lands, forest reserves of fishery reserves, but also marine waters included between two lines drawn perpendicularly to the general coastline from points where boundar y lines of the municipality or C ity touch the sea at low tide and the third line parallel with the general coastline and fifteen (15) kilometers from it. Where two (2) municipalities are so situated on the opposite shores that there is less than fifteen (15) kilometers of marine waters between them, the third line shall be equally dista nt from opposite shores of the respective municipalities; "Operator " includes the owner, manager, administrator, or any other person who operates or is responsible for the operation of a business establishment or undertaking; "Peddler " means any person who, either for himself or on commission, travels from place to place and sell his goods or offer to sell and deliver the same. Whether a peddler is a wholesale peddler or a retail peddler of a particular commodity shall be determined from the definition of wholesale dealer or retail dealer as provided on this Title; "Person s" means every natural or juridical being, susceptible of right of obligations or of being the subject of legal relations; "Residents " refer to natural persons who have their habitual residence in the province, C ity, or municipality where they exercise their civil rights and fulfil their civil obligations, and to juridical persons to which the law or any other provision creating or recognizing them fixes their residence in a particular province, C ity or municipality. In the absence of such law, juridical persons are residents of the province, C ity or municipality where they have their legal residence or principal place of business or where they conduct their principal business or occupation. “Reassessment ” is the assigning of a new assessed values to property, particularly real estate, as the result of a general, partial or individual re-appraisal of the property; “Remaining Economic Life ” is the period of time expressed in years from the date of appraisal to the date when the machinery becomes valueless; “Remaining Values ” is the value corresponding to the remaining useful life of the machinery; “Replacement or Reproduction Cost ” is the cost that would be incurred on the basis of current prices in acquiring an equally desirable property or the cost of reproducing a new replica of the property on the basis of current prices with the same or closely similar materials; and “Residential Land ” is land principally devoted to habitation. "Retail" means a sale where the purchaser buys the commodity for his own consumption, irrespective of the quantity of the commodity sold; "Vessel” includes every type of boat, craft, or other artificial contrivance used, or capable of being used, as a means of transportation on water. "Wharfage " means a fee assessed against the cargo of a vessel engaged in foreign or domestic trade based on quantity, weight or measure received and/or discharged by vessel; and "Wholesale " means a sale where the purchaser buys or imports the commodities for resale to persons other than the end user regardless of the quantity of the transaction. Page 6 of 137 Ordinance No. ______, Series 202 4 AN ORDINANCE ADOPTING THE 2024 REVISED PASAY CITY REVENUE CODE x------------------------------------x CHAPTER 2 REAL PROPERTY TAX Section 7. Administration of Real Property Tax. – The City shall be primarily responsible for the proper, efficient, and effective administration of the real property tax subject to the rules and regulation issued by the Department of Finance. Accordingly, the Department of Finance and the City shall exercise the authority to review and continuously examine the property, assessment, and real property tax records to ensure the proper implementation of this rule and determine compliance with existing laws and regulations. Section 8. Appraisal of Real Property. – All real property , whether taxable or exempt, shall be appraised at the current and fair market value prevailing in the C ity. The Department of Finance shall promulgate the necessary rules and regulations for the classification, appraisal , and assessment of real property pursuant to the provisions of the Local Government Code of 1991. Section 9. Real Property Identification System. – All declarations of real property made under the provisions of this Title shall be kept and filed under a uniform classification system to be established by the City Assessor. Section 10. Declaration of Real Property by the Owner or A dministrator. – It shall be the duty of all persons, natural or juridical, owning or administering real property, including the im provements therein, within the C ity or their duly authorized representative, to prepare, or cause to be prepared and file with the City Assessor, a sworn statement declaring the true value of their real property, whether previously declared or undeclared, taxable or exempt, which shall be the current and fair market value of the property, as determined by the declarant. Such declaration shall contain a description of the property sufficient in detail to enable the City Assessor or his deputy to identify the same for assessment purpose. The sworn declaration of real property herein referred to shall be filed with the City Assessor once every three (3) years during the period from January first (1 st) to June thirtieth (30th) commencing with the calendar year 1994. Failure by the owner or his duly authorized representative to file the same will be penalized by a fine of ₱50.00 for the first month; ₱100.00 for the second month; ₱ 200.00 for the third month; ₱ 300.00 for the fourth month; ₱ 400.00 for the fifth month; ₱ 500.00 for the sixth month; and so on for a maximum of ₱ 5,000.00, the proceeds of which will be added to the funds of the City Assessor’s Office. Section 11. Duty of Person Acquiring Real Property or Making Improvement T hereon. – It shall be the duty of any person or his authorized representative, acquiring at any time real property in the city, or making any improvements on real property to prepare or caused to be prepared and filed with the City Assessor, a sworn statement declaring the true value of subject property, within sixty (60) days after the acquisition of such property or upon completion or occupancy of the improvement, whichever comes earlier. In case of machinery, the sixty (60) days period of filing the required sworn declaration of property values shall commence on the date of installation thereof as determined by the City Assessor, for this purposes, the City Asses sor may secure certification from the City Engineer or othe r appropriate officials of the C ity. Failure to comply will result to the penalties mentioned in the next succeeding Section. Section 12. Proof of Exemption from Real Property Taxation. – Every person by or for whom real property is declared, who shall claim tax exemption for such property shall file with the City Assessor within thirty (30) days from the date of the declaration of real property sufficient documentary evidence in support of such claim including corporate charters, title of ownership, articles of incorporation, by laws, contracts, affidavits, certification and mortgage deeds, contracts, affidavits, certifications and mortgage deeds and similar documents. If the required evidence is not submitted within the period herein prescribed the property shall be listed as taxable in the Assessment Roll. However, if the property shall be proven to be exempt, the same shall be dropped from the Assessment Roll. Section 13. Dut y of the Registrar of Deeds to Appraise Assessor of Real Property Listed in R egistry. – a) Within six (6) months from the date of effectivity of the code, and/or before June 30 th of every year thereafter, the Registrar of Deeds shall prepare and submit to the City Assessor the abstract of his Registry of Property which shall include a brief but sufficient description of real properties entered therein, their Page 7 of 137 Ordinance No. ______, Series 202 4 AN ORDINANCE ADOPTING THE 2024 REVISED PASAY CITY REVENUE CODE x------------------------------------x present owners, and the date of their most recent transfer or alienation accompanied by copies of corresponding deed of sale, donation or partition or other form of alienation. b) Before any documents of transfer, alienation, or encumbrance of real property may be registered, the Registrar of Deeds shall require the presentation of a certificate or clearance issued by the City Treasurer to the effect that all current year and past year basic and additional SEF real property taxes, and the tax on transfer of real property ownership due on the subject, have been paid in full including interest or penalties due hereon. Failure to provide such certification shall be a valid cause for the Registrar of Deeds to refuse the registration of the documents. Without such certification or tax clearance, the registration is null and void. c) The Registrar of Deeds and notaries public shall furnish the City Assessor with copies of contracts, selling, transferring or otherwise conveying, leasing, or mortgaging real property registered by or acknowledged before them within thirty (30) days from the date of registration acknowledgment. Section 14. Duty of Official I ssuing Building Permit or Certificate of Registration of Machinery to Transmit Copy to A ssessor. – Any public official or employee who may now or hereafter be required by law or regulation to issue to any person a permit for the construction, addition, repair, or renovation of a building, or permanent improvement on land, or a certificate of registration for any machinery including machines, mechanical machine contrivances and app aratus attached or fixed on land or to another real property shall transmit within thirty (30) days of its issuance to the City Assessor. Section 15. Duty of Geodetic Engineer to F urnish Copy of the P lans to City Assessor. – It shall be the duty of all geodetic engineers, private or public, to furnish free of charge the City Assessor a white or blue print copy of each of all approved original or subdivision plans or maps of surveys executed by them within thirty (30) days from receipt of such plans from the Land Management Bureau, the Land Registration Authority, or the Housing and Land Use Regulatory Board, as the case may be. Section 16. Preparation of S chedule of Fair Market Value. – Before any general revision of property assessment is made pursuant to the provisions of this Code, there shall be prepared a schedule of fair market values by the City Assessor for the different classes of real property situated in the City for enactment by ordinance of the City Council. The schedule of fair market values shall be published in a newspaper of general circulation or in the absence thereof, shall be posted in the City Hall and in two (2) other conspicuous places in the City. Section 17. Classes of Real Property for Assessment Purposes. – For purposes of assessment, real properties shall be classified as residential, agricultural, commercial, industrial or special. Section 18. Special C lasses of Real Property. – All lands, buildings, and any improvements thereon actually directly and exclusively used for hospitals, cultural or scientific purposes, those owned and used by local water districts and government owned and controlled corporation rendering essential public services in the supply and distribution of water and/or generation of electric power shall be classified as special. Section 19. Actual U se of Real Property as Basis for Assessment. – Real property shall be classified, valued, and assessed on the basis of its actual use regardless of where located, whoever owns it, and whoever uses it. Section 20. Imposition of the B asic Real Property Tax. – There is hereby levied an annual ad valorem tax on the assessed value of real property such as land, building, machinery and the improvements affixed or attached to real property located in the City of Pasay at the following rates: CLASSES OF PROPERTY RATES OF LEVY Residential 1.5% Commercial 2% Industrial 2% Special 2% Section 21. Additional L evy on Real Property for the Special Education Fund (SEF). – There is hereby levied an annual tax of one percent (1%) on the assessed value of real property which shall be in addition to the basic real property tax. The proceeds thereof shall exclusively accrue to the Special Education Fund (SEF). Page 8 of 137 Ordinance No. ______, Series 202 4 AN ORDINANCE ADOPTING THE 2024 REVISED PASAY CITY REVENUE CODE x------------------------------------x All real property taxes which are not paid on time shall be subjected to a two percent (2%) penalty per month of unpaid amount of a fraction thereof until the date of delinquency until such taxes are fully paid. Provided, however, that in no case shall the total interest on the unpaid tax or portion thereof exceed thirty -six (36) months. Section 22. Valuation of Real Property. – In cases where (a) real property is declared and listed for taxation purposes for the first time; (b) there is an on -going general revision of property classification and assessment; (c) a request is made by the person in whose name the property is declared, the City Assessor or his duly authorized deputy shall, in accordance with the provisions of this chapter, make a classification, appraisal, and assessment of the real property listed and described in the declaration irrespective of any previous assessment or taxpayer’s valuation thereon. PROVIDED, however, that the assessment of real property shall not be increased often or more than once every three (3) years except in case of new improvements substantially increasing the value of said property or any change in its actual use. Section 23. Date of Ef fectivity of A ssessment or Re-assessment. – All assessment or re -assessment made after the first (1 st) day of any year shall take effect on the first (1st) day of January of the succeeding year. PROVIDED, however, that the re -assessment of real property due to its partial or total destruction, or to a major change in its actual use, or to any great sudden inflation or deflation of real property values, or to the gross illegality of the assessment when made or any other abnormal c | D2: Pasay | E2: 0.47402597 | F2: 56.7826
A3: 989 | B3: AN ORDINANCE PROVIDING FOR THE MODE AND AMOUNT OF PAYMENT FOR BUSINESS PLATE NUMBER REQUIREMENT OF ALL BUSINESS ESTABLISHMENTS IN PASAY CITY AS PER ORDINANCE NO. 977, SERIES OF 1997 WHICH REQUIRES ALL BUSINESS ESTABLISHMENTS AND OCCUPATIONAL UNDERTAKINGS TO REGISTER AND SECURE A BUSINESS PERMIT REGISTRATION PLATE BEFORE STARTING A BUSINESS IN THE CITY. | C3: a Mite’ a VAaw, — @ a, REPUBLIC OF THE PHILIPPINES OFFICE OF THE SANGGUNIANG PANLUNGSOD PASAY CITY, METRO MANILA ORDINANCE NO. 2389 1998 AN ORDINANCE PROVIDING FOR THE MODE AND AMOUNT OF PAYMENT FOR BUSINESS PLATE NUMBER REQUIREMENT OF ALL BUSINESS ESTABLISHMENTS IN PASAY CITY AS PER ORDINANCE NO. 977, SERIES OF WHICH REQUIRES ALL BUSINESS ESTABLISHMENTS AND OCCUPATIONAL UNDERTAKINGS TO REGISTER AND SECURE A BUSINESS PERMIT REGISTRATION PLATE BEFORE STARTING A BUSINESS IN THE 1997 CITY. SPONSORED BY: ACTING VICE MAYOR GREG F. ALCERA, COUNCILORS ROBERTO L. ALVAREZ AND EDITA V. VERGEL DE DIOS WHEREAS, there is a need to classify and stratify the amounts to be paid in | ; securing business permit registration plate depending upon the nature of business activity \|/. conducted in the City of Pasay. NOW THEREFORE, BE IT ORDAINED AS IT IS HEREBY ORDAINED, / \ by the Sangguniang Panlungsod of Pasay in session duly assembled to provide as it hereby _ provides the following schedule of assessments of payments that is to be enforced as the mode and amount of payments for the business license plate over and above other assessments for annual municipal licenses, to wit: A. FIRSTCLASS HOTELS -~____..................... NIGHT CLUBS, FIRST CLASS KARAOKE SAUNA BATH, BUS TERMINAL, ETC. B. MOTELS, BANKS —=ECL_..ny....... . cee eee TRAVEL AGENCY, RECRUITMENT AGENCY, PLACEMENT AND PROMOTION C. BEER HOUSE, MUSIC LOUNGE ___........... VIDEOKE, PAWNSHOP, RESTAURANT, MANUFACTURER, MONEY CHANGER, ETC. D. IMPORTER, EXPORTER, SERVICES __................. GEN. MERCHANIDISE, REAL ESTATE LESSOR, BOARDING HOUSE, TAILOR SHOP, DRESS SHOP, BARBER SHOP, HOT PANDESAL, PHOTO STUDIO, SECURITY, ETC. E. SARI-SARI STORE, CARENDERIA __............. REFRESHMENT STAND, LESSOR, ETC. Nineteen Hundred and Ninety-Eight. ENACTED, in Pasay City, this 12t'ay of January in the Year of Our Lord , REG K ALCERA WENCESLAO B. TRINIDAD APPROVED: HO Acting City Mayor Acting Vi P 3,000.00 2,000.00 1,000.00 500.00 300.00 6 ¢ Presiding Officer -page 2- Ordinance providing for the mode and amount of payment for business plate number requirement for all business establishments in Pasay City. 1. HON. ANTONINO G. CALIXTO 2. HON. EMMANUEL M. IBAY 3. HON. JUSTO C. JUSTO 4. HON. ROMULO M. CABRERA 5. HON. REYNALDO O. PADUA 6. HON. ROBERTO L. ALVAREZ 7. HON. EDITA V. VERGEL DE DIOS 8. HON. ULDARICO C. ARABIA 9. HON. ALBERTO V. PAREDES 10. HON. EDUARDO I. ADVINCULA 11. HON. TEQDULO R. LORCA 12. HON. GENEROSO F. CUNETA 13. HON. LEVINE A. CUNETA ATTESTED: | D3: Pasay | E3: 0.47402597 | F3: 56.7826
A4: 987 | B4: AN ORDINANCE PROVIDING FOR THE ADMINISTRATIVE SUPPORT SERVICES TO THE OFFICE OF SENIOR CITIZENS (OSCA) AND PROVIDING FUNDS THEREFORE. | C4: 1) REPUBLIC OF THE PHILIPPINES OFFICE OF THE PASAY CITY COUNCIL ORDINANCE NO. _98_7_ S-1998; ' AN ORDINANCE PROVIDING FOR THE ADMINISTRATIVE SUPPORT SERVICES TO THE OFFICE OF SENIOR CITIZENS (OSCA) AND PROVIDING FUNDS THEREFORE. Sponsored by Councilor Greg F. A/cera WHEREAS, Republic Act 7432 mandates the maximization of the contribution of Senior Citizens to society, and grants them special privileges and benefits, and the DILG Memo Circular No. 93-177 addressed to all local government units providing policy directions for the effective implementation ofRA7432 has already been effected; WHEREAS, Pasay City Ordinance No. 191 S-1993 has effected special privileges and the necessary framework to implement and effect RA 7432; WHEREAS, there is a need to preserve whatever gains was had in the organization of various Senior Citizen's groups in Pasay City, and ensure the delivery of basic services and privileges as mandated by law; NOW THEREFORE BE IT ORDAINED BY THE PASAY CITY COUNCIL IN A SESSION DULY ASSEMBLED THAT; 1.The Administrative Secretariat m1der the Office of Councilor Greg F. Alcera be maintained, and a majority of its personnel be manned by registered Pasay OSCA members; 2. The amount of PI43,000.00 be appropriated for the salaries and allowances of personnel to be designated to man the OSCA Office effective February -December, 1998. 3. The amount of P50,000.00 be appropriated for the purchase and/or printing of necessary documents and office supplies; 4.That the above-mentioned amounts be taken from the Special Projects Fund of the Office of the City Mayor and/or the proponent. APPROVED THIS 13th DAY OFJ am1.ary , 1998. �� HON. WENCESLAO TRINIDAD ACTING CITY MAYOR HON. GREG F. ALCERA HON. ANTONINO G. CALIXTO HON. EMMANUEL M. IBAY HON. JUSTO C. JUSTO HON. ROMULO M. CABRERA HON. REYNALDO 0. PADUA HON. ROBERTO L. ALVAREZ HON. EDITA VERGEL DEDIOS HON. ULDARICO C. ARABIA HON. ALBERTO V. PAREDES HON. EDUARDO I. ADVINCULA HON. TEODULO R. LORCA JR. HON. GENEROSOF.CUNETA HON. LEVINE CUNETA ATTESTED BY �: ___,,....., 0 .YAM SEC Y , .,, | D4: Pasay | E4: 0.47402597 | F4: 56.7826
A5: 986 | B5: ORDINANCE MANDATING THE OFFICE OF THE CITY ACCOUNTANT AND CITY TREASURER TO DEVIDE THE INTERNAL REVENUE ALLOTMENT (IRA) OF BARANGAY 183 ZONE 20 AND ALLOCATE A PORTION THEREOF TO BARANGAY 201, ZONE 20, PASAY CITY IN ACCORDANCE WITH NUMBER OF POPULATION OF SAID BARANGAYS | C5: 8 couc OF THE omen SANGGUNIANG PANLUNGSOD PASAY CITY ORDINANCE NO. 986 _,S. 1998 ORDINANCE MANDATING THE OFFICE OF THE CITY ACCOUNTANT AND CITY TREASURER TO DEVIDE THE INTERNAL REVENUE ALLOTMENT (IRA) OF BARANGAY 183, ZONE 20 AND ALLOCATE A PORTION THEREOF TO BARANGAY 201, ZONE 20, PASAY CITY IN ACCORDANCE WITH NUMBER OF 3 POPULATION OF SAID BARANGAYS. ) Sponsored by: Acting Vice Mayor GREG F. ALCERA and Councilors ROMULO M. CABRERA, EDITA V. VERGEL DE DIOS, ANTONINO G. CALIXTO, ULDARICO C. ARABIA, REYNALDO O. PADUA, JUSTO C. JUSTO, TEODULO R. LORCA, JR. ROBERTO L. ALVAREZ, EMMANUEL M. IBAY, EDUARDO I. ADVINCULA, , ALBERTO B. PAREDES, GENEROSO F. CUNETA and LEVINE A. CUNETA WHEREAS, pursuant to Ordinance No. 831, S. 1997, the areas of Teachers Bliss, Kalayaan Village and Balagbag was segregated from barangay 183 and Barangay 201 was created out of the said segregated areas; WHEREAS, the Internal Revenue Allotment of Barangay 183 for the year 1998 is * = computed at FOUR MILLION EIGHT HUNDRED TWENTY THOUSAND SIX S HUNDRED THIRTY EIGHT (P4,820,638.00) PESOS which allotment includes the share of Barangay 201; WHEREAS, the number of population of Barangay 201 as per Census of September 1, 1995 is ELEVEN THOUSAND THREE HUNDRED EIGHTY FIVE (11,385) inhabitants _. while that of Barangay 183 is THIRTY FOUR THOUSAND THREE HUNDRED FORTY EIGHT (34,348) inhabitants; WHEREAS, there is a need for the Office of the City Treasurer to devide the Internal Revenue Allotment of Barangay 183 and allot a portion thereof to Barangay 201 in accordance with their respective number of population. NOW THEREFORE, be it ORDAINED, as it is hereby ORDAINED, in session duly ~\ assembled that: SECTION 1- COMPUTATION OF INTERNAL REVENUE ALLOTMENT (IRA)- The Office of the City Accountant and City Treasurer are hereby mandated to devide the IRA of Barangay 183 and allot a portion thereof to Barangay 201 computed in accordance “——LArwith their respective number of population to wit: NO. OF POPULATION 1998 IRA SHARE BARANGAY 183 34,348 Inhabitants P3,620,565.00 BARANGAY 201 11,385 Inhabitants P1,200,073.00 - which Internal Revenue Allotment (IRA) is to be released every quarter to said Barangays; SECTION 2- EFFECTIVITY- This Ordinance shall take effect upon its approval and publication in a newspaper of general circulation in Pasay City; ENACTED in the City of Pasay this 6th day of aay in the Year of Our Lord Nineteen Hundred and Ninety Eight. oR eae HON. WENCESLAO B. TRINIDAD Acting City Mayor Ac fLON. GREG\F. ALCERA ng Vice Mayor & Presiding Officer -Page 2- 8 : 5 (Ordinance No. _, S. 1998) 1. Hon. ANTONINO G. CALIX = 2. Hon. EMMANUEL M. IBAY Scan 2S 3. Hon. JUSTO C. JUSTO YA 4. Hon. ROMULO M. CABRERA <fs f Vege 5. Hon. REYNALDO O. PADUA We e 6. Hon. ROBERTO L. ALVAREZ Ohl 7. Hon. EDITA V. VERGEL DE DIOS Z/ L Prod 8. Hon. ULDRICO C. ARABIA 9. Hon, ALBERTO V. PAREDES 10. Hon. EDUARDO I. ADVINCULA 11. Hon. TEODULO R. LORCA, 12. Hon. GENEROSO F. CUNETA 13. Hon. LEVINE A. CUNETA ATTESTED BY: ATTX. ROBER YO B. YAM City Sécfetary REPUBLIC OF THE PHILIPPINES SANGGUNIANG PANLUNGSOD _ PASAY CITY ORDINANCE NO.984, $-1997, = AN ORDINANCE FURTHER AMENDING ORDINANCE NO. 267, S-1994 DECLARING VERGEL STREET FROM TRAMO STREET TO TAFT AVENUE FROM 6:00 A.M. TO 6:00 P.M. AS NO PARKING ON BOTH SIDES. Sponsored by: Councilors Romulo M. C C. Arabia and Antonino G. Calixto abrera, Edita V. Vergel de Dios, Uldarico WHEREAS, Barangays 98 and 99, Zone 14, Pasay City passed resolution seeking to declare Vergel Street from Tramo Street to Taft Avenue as no parking on both sides from 6:00 A.M. to 8:00 P.M.; WHEREAS, the COMMITTEE ON TRANSPORTATION recommeded to the SANGGUNIANG PANLUNGSOD to amend Ordinance No. 267, S-1994 to declare the entire length of Vergel Street in the provisio of NO PARKING ON BOTH SIDES, NOW THEREFORE , BE IT RESOLVED AS IT IS HEREBY RESOLVED in session duly assembled that: SECTION L Section 6.25 of Ordinance No. 267, S-1994 is hereby amended to ‘read as follows: . “SECTION 6.25 - Vergel Street from Cabrera Street to Taft Avenue from 6:00 A.M. to 8:00 P.M.” SECTION 2, EFFECTIVITY - This Ordinance shall take effect upon its approval and publication ina newspaper of general circulation in Pasay City. DONE in the City of Pasay this 16th day of December in the Year of Our Lord Nineteen Hundred and Ninety Seven. APPROVED: ‘ ‘A HON. WENCESLAO B. TRINIDAD Acting City Mayor A. HON. ANTONINO G.CALIXTO 2. HON. EMMANUEL M. IBAY PAGE 2 of Ordinance No 984,S1997 Ordinance further amending Ordinance No 267, S-994 declaning Verge! Street From Tramo Sueetto Taf Avenue from 600 A.M. to800PM asno parking on both sides 3. HON. JUSTO C. JUSTO 4. HON. REYNALDO O. PADUA 5. HON. ROMULO M. CABRERA | 6. HON. ROBERTO L. ALVAREZ 4 HON. EDITA V.VERGEL DE DIOS 8. HON. ULDARICO C. ARABIA 2: HON. ALBERTO V. PAREDES : 10. HON. EDUARDO L ADVINCULA _ Il. HON. TEODULO R. LORCA JR. 12. HON. GENEROSO F. CUNETA 13. HON. LEVINE A. CUNETA “,0VED ORDINANCE - ) ASAY ‘8. Hon. ULDRICO C. ARABIA ALPPA TIMES ~ Jan. 22-31, 1998 SANGGUNIANG PANLUNGSOD PASAY. CITY ORDINANCE NO. 986_, S. 1998 E DATING THE OFFICE OF THE CITY ACCOUNTANT AND CITY TREASURER TO DEVIDE THE INTERNAL REVENUE ALLOTMENT (IRA) OF BARANGAY 183, ZONE 20 AND ALLOCATE A PORTION THEREOF TO BARANGAY 201, ZONE 20, PASAY CITY IN ACCORDANCE WITH NUMBER OF POPULATION OF SAID BARANGAYS. ? Sponsored by: Acting Vice Mayor GREG F. ALCERA and Councilors ROMULO M. CABRERA. EDITA v. VERGEL DE DIOS, ANTONINO G. CALIXTO, ULDARICO C. ARABIA, REYNALDO O. PADUA, JUSTO C. JUSTO, TEODULO R. LORCA, JR. ROBERTO L. ALVAREZ, EMMANUEL M. IBAY, EDUARDO I. ADVINCULA, , ALBERTO B. PAREDES, GENEROSO F: CUNETA and LEVINE A. CUNETA WHEREAS, pursuant to Ordinance No. 831, S. 1997, the areas of Teachers Bliss, Kalayaan Village and’ Balagbag was sceregatcd from barangay 183 and Barangay 20! was created out of the said segregated areas; WHEREAS, the Internal Revenue Allotment of Barangay. 183 for the year 1998 is computed at FOUR MILLION EIGHT HUNDRED TWENTY THOUSAND SIX HUNDRED THIRTY EIGHT (P4,820,638.00) PESOS which allotment includes the share of Barangay 201; WHEREAS, the number of population of Barangay 20) as per ier of September 1, 1995 is ELEVEN THOUSAND THREE HUNDRED EIGHTY FIVE (11,385) ‘inhabitants while that of Barangay 183 is THIRTY FOUR THOUSAND THREE HUND D FORTY EIGHT (34,348) inhabitants; WHEREAS, there is a need for the Office of the City Treasurer to devide the Internal Revenue Allotment of Barangay 183 and allot a portion thereof to Barangay 201 in accordance with their réspective number of population. NOW THEREFORE, be it ORDAINED, as it is hereby ORDAINED, in session duly assembled that: SECTION 1- COMPUTATION OF INTERNAL REVENUE ALLOTMENT (IRA)- The Office of the City Accountant and City Treasurer are hereby mandated to devide the IRA of Barangay 183 and allot a portion thereof to Barangay 201 computed in accordance with their respective number of population to wit: : NO. OF POPULATION 1998 IRA SHARE BARANGAY 183 34,348 Inhabitants P3,620,565.00 BARANGAY 20! 11,385 Inhabitants P1,200,073.00 which Internal Revenue Allotment (IRA) is to be released every quarter to said Barangays; SECTION 2- EFFECTIVITY- This Ordinance shall take effect upon its approval and publication in a newspaper of general circulation in Pasay City; ENACTED in the City of Pasay this 6th day of January-in the Year of Our Lord Nineteen Hundred and Ninety Eight. APPROVED: » HON. WENCESLAO B. TRINIDAD Acting City Mayor Act *- 1. Hon. ANTONINO G. CALI 2. Hon. EMMANUEL M. IBAY 3. Hon. JUSTO C. JUSTO 4. Hon. ROMULO M. CABRERA _ 5, Hon. REYNALDO O. PADUA 6. Hon. ROBERTO L, ALVAREZ 7. Hon. EDITA V. VERGEL DE DIOS 9. Hon. ALBERTO V. PAREDES 10. Hon. EDUARDO I. ADVINCULA II. Hon. TEODULO R. LORCA, 12. Hon. GENEROSO F. CUNETA _ 13. Hon. LEVINE A. CUNETA ATTESTED BY: ATTX. ROBE B. YAM City Sdefetary | D5: Pasay | E5: 0.47402597 | F5: 56.7826
A6: 984 | B6: AN ORDINANCE FURTHER AMENDING ORDINANCE NO. 267, S-1994 DECLARING VERGEL STREET FROM TRAMO STREET TO TAFT AVENUE FROM 6:00 AM TO 6:00 PM AS NO PARKING ON BOTH SIDES. | C6: REPUBLIC OF THE PHILIPPINES SANGGUNIANG PANLUNGSOD PASAY CITY ORDINANCE NO.984, S-1997 ORDINANCE FURTHER AMENDING ORDINANCE NO. 267, S-1994 DECLARING VERGEL STREET FROM TRAMO STREET TO TAFT AVENUE FROM 6:00 AJM. TO 6:00 PJVL AS NO PARKING ON BOTH SIDES. Sponsored by: Councilors Romulo M. Cabrera, Edita V. Vergel de Dios, Uldarico C. Arabia and Antonino G. Calixto WHEREAS, Barangays 98 and 99, Zone 14, Pasay City passed resolution seeking to declare Vergel Street from Tramo Street to Taft Avenue as no parking on both sides from 6:00 AM . to 8:00 P.M.; WHEREAS, the COMMITTEE ON TRANSPORTATION recommeded to the SANGGUNIANG PANLUNGSOD to amend Ordinance No. 267, S-1994 to declare the entire length of Vergel Street in the provisio of NO PARKING ON BOTH SIDES; NOW THEREFORE , BE IT RESOLVED AS IT IS HEREBY RESOLVED in session duly assembled that: SECTION 1 . Section 6.25 of Ordinance No. 267, S-1994 is hereby amended to read as follows: “SECTION 6.25 - Vergel Street from Cabrera Street to Taft Avenue from 6:00 AM . to 8:00 P.M.” SECTION 2. EFFECTIVITY - This Ordinance shall take effect upon its approval and publication in a newspaper of general circulation in Pasay City. DONE in the City of Pasay this 16th day of December in the Year of Our Lord Nineteen Hundred and Ninety Seven. APPROVED: [ON. WENCESLAO B. TRINIDADActing City Mayor>N . GREG W. ALCERA Actji Vice-Mayor'# Presiding Officer 2.HON. ANTONINO G.CAUXTO HON. EMMANUEL M. IBAY PAGE 2 of Ordinance No. 984, S-1997 Ordinance further amending Ordinance No. 267, S-1994 declaring Verge! Street From Tramo Street to Taft Avenue from 6:00 A M . to 8:00 P M. as no parking on both sides. 3. 4. 5. 6. 7. 8. 9.HON. JUSTO C. JUSTO HON. REYNALDO O. PADUA HON. ROMULO M. CABRERA HON. ROBERTO L. ALVAREZ ATTESTED: | D6: Pasay | E6: 0.47402597 | F6: 56.7826
A7: 981 | B7: AN ORDINANCE EXTENDING THE DEADLINE OF DECEMBER 31, 1997 FOR THE PAYMENT OF LAND TAX FOR THE YEAR 1997 AND ,THE DEADLINE OF JANUARY 20, 1998 FOR THE PAYMENT OF BUSINESS LICENSES, BOTH, TO JANUARY 31, 1998. | C7: ® REPUBLIC OF THE PHILIPPINES OFFICE OF THE SANGGUNIANG PANLUNGSOD PASAY CITY, METRO MANILA SA ORDINANCE NO. 981 - S 1997 IN AN ORDINANCE EXTENDING THE DEADLINE OF DECEMBER 31, 1997 FOR THE PAYMENT OF LAND TAX FOR THE YEAR 1997 AND THE DEADLINE OF ¢ JANUARY 20, 1998 FOR THE PAYMENT OF BUSINESS LICENSES, BOTH, TO ; JANUARY 31, 1998. \ Sponsored by: Acting Vice Mayor GREG F. ALCERA, Councilors ANTONINO G. CALIXTO, EMMANUEL M. IBAY, JUSTO C. JUSTO, ROMULO M. CABRERA, REYNALDO O. PADUA, ROBERTO L. ALVAREZ, EDITA V. VERGEL DE DIOS, ULDARICO C. ARABIA, ALBERTO V. PAREDES, EDUARDO I. ADVINCULA, \|__TEODULO R. LORCA JR., GENEROSO F. CUNETA and LEVINE A. CUNETA WHEREAS, Section 167 of the Local Government Code of 199] provides that a local government unit 1s expressly authorized to either extend the deadline for the payment of local taxes or even waive the payment of interest, surcharges, or penalties on delinquent fn taxes; - i WHEREAS, for the year 1997, considering that there is still a substantial number ING of taxpayers who has not yet paid their corresponding real property tax and who may opt Ry to pay the same on the last day of the current year, but would unable to do so because of so many legal holidays during the month of December 1997, it would be for the benefits of the taxpayers if the deadline for the real property tax and business licenses be extended to January 31, 1998. . 3 N NOW, THEREFORE, BE IT ORDAINED BY THE PASAY CITY 1 COUNCIL IN SESSION DULY ASSEMBLED THAT; | i Section 1. Extension of Deadline for the Payment of Local Taxes and ‘ie Licenses - The payment of land tax corresponding to the Year 1997 which will expire on December 31, 1997 is hereby extended up to January 31, 1998 and the payment of business licenses which will expire on January 20, 1998 is hereby extended up to January 31, 1998. + Section 2. Effectivity - This ordinance shall take effect upon passage and (}\ approval of the Sangguniang Panlungsod, approval of the City Mayor and its publication oS in a newspaper of general circulation in the city. Fa ENACTED in Pasay City, this 12" day of December in the Year of Our Lord, / _|Nineteen Hundred and Ninety-Seven. ¥ 4 y , APPROVED: Laney a HON. WENCESLAO B. TRINIDAD By. Acting City Mayor -page 2- Ordinance 981 Series of 1997 1. HON. ANTONINO G. CALIXTO 2. HON. EMMANUEL M. IBAY 3. HON. JUSTO C. JUSTO 4. HON. ROMULO M. CABRERA 5. HON. REYNALDO O. PADUA 6. HON. ROBERTO L.. ALVAREZ 7. HON. EDITA V. VERGEL DE DIOS 8. HON. ULDARICO C. ARABIA 9: HON. ALBERTO V. PAREDES 10. HON. EDUARDO I. ADVINCULA 11. HON. TEODULO R. LORCA 12. HON. GENEROSO F. CUNETA 13. HON. LEVINE A. CUNETA ATTESTED: ATTY. ROBERTO B. YAM City Secretary ra | D7: Pasay | E7: 0.47402597 | F7: 56.7826
A8: 980 | B8: AN ORDINANCE APPROPRIATING THE AMOUNT OF TWENTY THOUSAND PESOS (P20,000.00) AS FINANCIAL ASSISTANCE TO THE HEIRS OF BARANGAY TANOD GONZALO LUCERIO OF BARANGAY 26, PASAY CITY WHO DIED IN LINE OF DUTY. | C8: A } REPUBLIC OF THE PHILIPPINES SANGGUNIANG PANLUNGSOD PASAY CITY, METRO MANILA ORDINANCE NO. 980 S-1997 INANCE APPROPRIATING THE AMOUNT OF TWENTY THOUSAND (P20,000.00) AS FINANCIAL ASSISTANCE TO THE HEIRS OF RANGAY TANOD GONZALO LUCARIO OF BARANGAY 26, PASAY CITY, WHO DIED IN LINE OF DUTY. Sponsored by: Acting Vice Mayor GREG F. ALCERA, Councilors ANTONINO G. CALIXTO, ROMULO M. CABRERA, EMMANUEL M. IBAY, REYNALDO O. PADUA, JUSTO C. JUSTO, ROBERTO L. ALVAREZ, EDITA V. VERGEL DE DIOS, ULDARICO C. ARABIA, ALBERTO V. PAREDES, EDUARDO I. ADVINCULA,, TEODULO R. LORCA, JR., GENEROSO F. CUNETA and LEVINE A. CUNETA. WHEREAS, Gonzalo Lucario of Barangay 26, Pasay City, is a Barangay Tanod, who died while in the performance of his duty; WHEREAS, the heirs of the said barangay tanod was left to shoulder and defray the expenses incurred from the untimely death of the mentioned tanod who just responded to the call of duty as a barangay official; WHEREAS, the death of Gonzalo Lucario 1s a great loss to the family and to the barangay. NOW THEREFORE BE IT ORDAINED AS IT IS HEREBY ORDAINED, by the Sangguniang Panlungsod of Pasay in session duly assembled to appropriate as it hereby appropriates the amount of Twenty Thousand Pesos (P20,000.00) as financial assistance to the heirs of Barangay Tanod Gonzalo Lucario of Barangay 26, Pasay City. ENACTED in Pasay City, this 9" day of December, in the Year of Our Lord Nineteen Hundred and Ninety-Seven. APPROVED: ATTY. WENCESLAO B. TRINIDAD Acting City Mayor 7, ALCERA & Presiding Officer 1. HON. ANTONINO G. CALIXTO 2. HON. EMMANUEL M. IBAY 3. HON. JUSTO C. JUSTO -page 2- ORD. No. 980 Series of 1997 10. 11. LZ. HON. ROMULO M. CABRERA . HON. REYNALDO O. PADUA HON. ROBERTO L. ALVAREZ HON. EDITA V. VERGEL DE DIOS HON. ULDARICO C. ARABIA HON. ALBERTO V. PAREDES HON. EDUARDO I. ADVINCULA HON. TEODULO R. LORCA, JR. HON. GENEROSO F. CUNETA . HON. LEVINE A. CUNETA ATTESTED BY: —- ATTY. ROBERTO B. YAM City Secretary Wi | D8: Pasay | E8: 0.47402597 | F8: 56.7826
A9: 978 | B9: ORDINANCE ENACTING RULES AND REGULATIONS IN THE PAYMENT OF ALLOWANCES TO POLICE OFFICERS AND PERSONNEL'S ASSIGNED IN PASAY CITY | C9: O05 LIC OF THE pETLIPPra SANGGUNIANG PANLUNGSOD PASAY CITY r | ORDINANCE NO. 978; S. 1997 } | v ORDINANCE ENACTING RULES AND REGULATIONS IN THE . PAYMENT OF ALLOWANC TO POLICE OFFICERS AND \ PERSONNEL’S ASSIGNED IN PASAY CITY Sponsored by: Acting Vice Mayor GREG F, ALCERA, Councilors ROMULO M. CABRERA. ANTONINO G. CALIXTO, ULDARICO C. ARABIA, JUSTO C. JUSTO, EDUARDO I. ADVINCULA, REYNALDO O. PADUA, EMMANUEL M. IBAY, ROBERTO L. ALVAREZ, LEVINE A. CUNETA, GENEROSO F. CUNETA, EDITH V. VERGEL DE DIOS, ALBERTO V.PAREDES and TEODULO R. LORCA. WHEREAS, the City Mayor is vested with operational supervision and control over police units assigned in Pasay City; WHEREAS, the SANGGUNIANG PANLUNGSOD has enacted Resolution No. 945, S-1997, strongly requesting the Philippine National Police (PNP) Regional Directorate to assign and deploy in Pasay City only police officers and personnel who are residents of Pasay City for at least ONE (1) year prior to deployment; , \ WHEREAS, Notwithstanding the aforesaid resolution the PNP Directorate continue NW to assign and deploy police officers and personnel in the City who lack ONE (1) year N residency in Pasay City; SFY) WHEREAS, the City Government has been paying allowances to all police officers S&T /and personnel performing duties in Pasay City; WHEREAS, there is a need to enact rules and regulations in the payment of allowance to police officers and personnel to give teeth to Resolution No. 945; S-1997 so that its intention be satisfied and complied with; NOW THEREFORE, be it ORDAINED as it is hereby ORDAINED, in session duly assembled that: SECTION 1. ALLOWANCE - all police officers and personnel presently assigned and fe deployed in Pasay City shall be entitled to payment of existing allowance being provided by - the City Government, except those assigned and deployed after the effectively of this / | Ordinance and has not acquired ONE (1) year residing prior to assignment and deployment; / SECTION 2.- PROOF OF RESIDENCY - All police officers and personnel who ue ; assigned and deployed after the effectivity of this ordinance must show proof of residency) | consisting of Certification from the COMELEC of Pasay City and /or from the Barangay | Chairman of the place where the assignee is residing to be submitted to the Office of the \ 4 Mayor and Treasurer, respectively; < SECTION 3.-ACQUISITION OF ONE (1) YEAR RESIDENCY - AIl police officers and personnel assigned and deployed after the effetivity of this ordinance and who has not qualified for payment of the allowance, shall after ONE (1) year of continuos residency in Pasay City shall qualify for payment of existing allowances; SECTION 4.. AMENDMENT/REPEAL - Any existing ordinance or provision thereof inconsistent with any provision of this ordinance are hereby deemed amended or repealed; -Page 2- (Ordinance No. “ 1997) 8. 9. . Hon . Hon . Hon . Hon Hon Hon . Hon Hon Hon SECTION 5.- Any police officers and personnel assigned and deployed in Pasay City after the effectivity of this ordinance and who misrepresent himself to be a resident of Pasay City in order to qualify for payment of allowance being provided by the City and COMELEC personnel and Barangay Chairman who falsely certify to the required residency shall suffer the penalty of of ONE (1) year imprisonment; SECTION 6.- EFFECTIVITY - This ordinance shall take effect immediately upon its approval ; ENACTED in the City of Pasay this 3rd day of December in the Year of Our Lord Nineteen Hundred and Ninety Seven, APPROVED: HON. WENCESLAO B. TRINIDAD H Acting City Mayor Acting ee ES aa. \ v.+,°4 . ANTONINO G. CALIXTO Ba . EMMANUEL M. IBAY ~~ Yl ~-CjZ > , JUSTO C. JUSTO Ataaw . ROMULO M. CABRERA | ee et er , REYNALDO O. PADUA Ke ee “si . ROBERTO L. ALVAREZ . ba . EDITA V. VERGEL DE DIOS ,ULDRICO C. ARABIA ae _ ALBERTO V. PAREDES AY 10, Hon. EDUARDO I. ADVINCULA 11. Hon. TEOQDULO R. LORCA, JR. 12. Hon. GENEROSO F. CUNETA 13. Hon. LEVINE A, CUNETA ALTESTED: BY: ATTY. ROBER10 B. YAM City Secretary | D9: Pasay | E9: 0.47402597 | F9: 56.7826
A10: 969 | B10: AN ORDINANCE CREATING THE PERSONNEL SELECTION AND PROMOTION BOARD TO ASSIST THE LOCAL CHIEF EXECUTIVE IN THE JUDICIOUS AND OBJECTIVE SELECTION OF PERSONNEL FOR EMPLOYMENT AS WELL AS FOR PROMOTION AND IN THE FORMULATION OF SUCH POLICIES AS WOULD CONTRIBUTE TO EMPLOYEE WELFARE. | C10: REPUBLIC OF THE PHILIPPINES OFFICE OF THE SANGGUNIANG PANLUNGSOD PASAY CITY, METRO MANILA ORDINANCE NO. 969 S-1997 AN ORDINANCE CREATING THE PERSONNEL SELECTION AND PROMOTION BOARD TO ASSIST THE LOCAL CHIEF EXECUTIVE IN THE JUDICIOUS AND OBJECTIVE SELECTION OF PERSONNEL FOR EMPLOYMENT AS WELL AS FOR PROMOTION AND IN THE FORMULATION OF SUCH POLICIES AS WOULD CONTRIBUTE TO 8 EMPLOYEE WELFARE. Sponsored by: Acting Vice Mayor GREG F. ALCERA \ 4K WHEREAS, paragraph (a), Article 166 of the Rules and Regulations ( =N mplementing the Local Gov’t. Code of 1991 states that “there shall be established in every province, city or municipality, a personnel selection board to assist the local chief 'N’ executive or, where applicable, the presiding officer of the sanggunian in the judicious and objective selection of personnel for employment as well as for promotion;” WHEREAS, paragraph (b) of the same article provided that “the personnel selection board shall be composed of the City Mayor, City Vice Mayor. Chairman, Committee on Civil Service, Chairman, Committee on Appropriation, City Personnel Officer and representative of Civil Service Commission as the ex officio member of the board,” WHEREAS, par. ©, as the succeeding paragraph, also states that “personnel selection and Promotion Board shall formulate screening procedures and shall adopt criteria for evaluating candidates for employment or promotion in the first and second levels of the local government career service;” WHEREAS, “par. (d), the last paragraph of Article 166, states that “the personnel selection board shall formulate policies on employee welfare in accordance with civil service law, rules and regulations;” WHEREAS, the creation of the said office shall be the screening body in evaluating the personnel for employment. NOW THEREFORE, BE IT ORDAINED AS IT IS HEREBY ORDAINED, by the Sangguniang Panlungsod of Pasay in session duly assembled to create as it hereby creates the Office of the Personnel Selection and Promotion Board to assist the local chief executive in the judicious and objective selection of personnel for employment as well as for promotion and in the formulation of such policies as would contribute to employee welfare. ENACTED in Pasay City, this 4th day of November in the Year of our Lord Nineteen Hundred and Ninety Seven. APPROVED: dos HON. WENCESLAO B. TRINIDAD Acting City Mayor . ALCERA Vice Vpyer FP -page 2- An Ordinance creating the Office of the Personnel Selection Board to assist the local chief executive in the judicious and objective selection of personnel for employment as well as for promotion and in the formulation of such policies as would contribute to employee welfare. 10. Ld: Le. 13: HON. ANTONINO G. CALIXTO HON. EMMANUEL M. IBAY HON. JUSTO C. JUSTO HON. ROMULO M. CABRERA HON. REYNALDO O. PADUA HON. ROBERTO L. ALVAREZ HON. EDITA V. VERGEL DE DIOS HON. ULDARICO C. ARABIA HON. ALBERTO V. PAREDES HON. EDUARDO I. ADVINCULA HON. TEODULO R. LORCA, JR. HON. GENEROSO F. CUNETA HON. LEVINE A. CUNETA AFTESTED: ‘ E B. YAM City Secretary Valu W (/ Sh ot Df MY i lal // ~~ \ Dv i vy wk | D10: Pasay | E10: 0.47402597 | F10: 56.7826
A11: 968 | B11: ORDINANCE MANDATING THE CITY TREASURER TO DEPUTIZE BARANGAY TREASURERS TO COLLECT COMMUNITY TAX PAYABLE BY INDIVIDUAL TAX PAYERS | C11: REPUBLIC OF THE PHILIPPINES SANGGUNIANG PANLUNGSOD PASAY CHY IN ( } ORDINANCE NO. 968 _, 8. 1999 Be SX ORDINANCE MANDATING THE CITY TREASURER TO s DEPUTIZE BARANGAY TREASURERS TO COLLECT COMMUNITY TAX PAYABLE BY INDIVIDUAL TAX PAYERS Sponsored by: Councilor ROMULO M. CABRERA and Acting Vice Mayor GREG F. ALCERA, Councilors ULDARICO C. ARABIA, ANTONINO G. CALIXTO, GENEROSO F. CUNETA, JUSTO C. JUSTO, EMMANUEL M. _ IBAY, TEODULO R. LORCA, JR., EDUARDO I. ADVINCULA, LEVINE A. CUNETA, EDITA V. VERGEL DE DIOS, REYNALDO O. PADUA, ROBERTO L. ALVAREZ and ALBERTO V. PAREDES WHEREAS, it is the policy of the State to provide Local Government Unit for a genuine and meaningful local autonomy to enable them to attain their fullest development as a self reliant community; WHEREAS, towards this end, the State shall provide a more responsive and accountable local government structure instituted through a _= system of descentralization; WHEREAS, the barangays as a Local Government Unit and as partners for progress of Pasay City need be given more powers, authority, responsibilities and resources for them to attain their fullest development; WHEREAS, the Local Government Code of 1991 authorized the City Treasurer to deputize Barangay Treasurers who are properly bonded, to collect community tax payable by individual tax payers if the former is authorized by the ordinance levying said tax; NOW THEREFORE, be it ORDAINED, as it is hereby ORDAINED, in session duly assembled, that: SECTION 1. DEPUTIZATION AND SCOPE OF AUTHORITY. - The City Treasurer is mandated to deputize Barangay Treasurers to collect community tax, payable by individual tax payers only; SECTION 2. QUALIFICATION. - The deputized Barangay Treasurer must 3 post cash bond not less than FIVE THOUSAND (P5,000.00) PESOS and must attend orientation to be conducted by the Office of the City Treasurer on the issuance of * Community Tax Certificate; SECTION 3: REQUISITION OF COMMUNITY TAX FORMS, - The deputized Barangay Treasurer shall secure or requisition on consignment, from the City Treasurer the blank forms of Community Tax Certificates and shall pay the co of printing and distribution thereof pursuant to Section 6 hereof; ws SP oe -Page 2- (Ordinance No. Tb bf S-1997) SECTION 4. JURISDICTION. - The deputized Barangay Treasurer shall only collect Community Tax within the territorial jurisdiction of the barangay; SECTION 5. REMITTANCE OF PROCEEDS. - The deputized Barangay Treasurer shall turn over the proceeds of community tax collection every end of the month, rendering a monthly accounting of the collection, together with the duplicates of the Community Tax Certificate issued. The City Treasurer shall prepare the necessary forms for purposes of accounting; SECTION 6. ALLOCATION OF PROCEEDS OF COMMUNITY TAX. - The proceeds of community tax collected through the Barangay Treasurer shall be apportioned each quarter, as follows: a) Fifty percent (50%) shall accrue to the general fund of the City of Pasay; b) Fifty percent (50%) shall accrue to the general fund of the barangay were the tax was collected, less the cost of printing and distribution of the requisitioned blank form of the Community Tax Certificates; SECTION 7. RESCISSION OF AUTHORITY AND CONFISCATION OF CASH BOND. - Mere delay in the remittance of the proceeds of collection pursuant to Section 5 hereof is sufficient ground for the City Treasurer to rescind the authority to collect community tax and confiscate the cash bond posted by the Barangay Treasurer; SECTION 9. EFFECTIVITY. - This ordinance shall take effect immediately upon its approval and publication in a news paper of general circulation in the City of Pasay; DONE in the City of Pasay this 27th day of October in the Year of Our Lord Nineteen Hundred and Ninety Seven. APPROVED: Wau DM Lo HON. WENCESLAO B. TRINIDAD Acting City Mayor 1. Hon. ANTONINO G. CALIXTO 2. Hon, EMMANUEL M. IBAY 3. Hon. JUSTO C. JUSTO 4, Hon. ROMULO M. CABRERA 5. Hon. REYNALDO O. PADUA 6. Hon. ROBERTO L, ALVAREZ -Page 3- (Ordinance No. » 92-1997) 7. Hon. EDITA V. VERGEL DE DIOS / / 8. Hon. ULDRICO C. ARABIA Arn awA Po : 9. Hon. ALBERTO V. PAREDES 10. Hon. EDUARDO I. ADVINCULA___ex fa, 11, Hon. TEODULO R. LORCA, JR. ee sR, Ee gs , ose 12, Hon. GENEROSO F. CUNETA Se eS , 13. Hon. LEVINE A. CUNETA aa a ATTESTED -BY: Ma. LOURDES F. CABRIDO ATTY. ROBERTO B. YAM OIC - City Administrator City Secretary we all | D11: Pasay | E11: 0.47402597 | F11: 56.7826
A12: 963 | B12: AN ORDINANCE EXEMPTING ALL LEGITIMATE COOPERATIVES, REGISTERED AND OPERATING WITHIN THE CITY OF PASAY FROM ALL TAXES, FEES AND ANY DUES IMPOSED BY THE CITY GOVERNMENT | C12: Republic o f the Philippines OFFICE OF THE CITY COUNCIL Pasay City,M etro M anila ORDINANCE NO. 963 .S-1997 AN ORDINANCE EXEM PTING ALL LEGITIM ATE COOPERATIVES, REGISTERED AND OPERATING W ITHIN THE CITY O F PASAY FROM ALL TAXES, FEES AND ANY DUES IM POSED BY THE CITY GOVERNMENT are registered with the Cooperative Development Authority ( CDA ) and operating within the City o f Pasay, and their number still increasing; W HEREAS, many o f these legitimate Cooperatives have not complied with the Bureau o f Internal Revenue ( BIR ) requirement; W HEREAS, the foregoing non-compliance was found out to be the result of Cooperatives failure to secure business and / or Mayors Permit from the Local Government due Cooperative Code o f the Philippines and Bureau o f Local Government Finance Memo Circular No. 02-97 provide that cooperatives shall not be subject to any government taxes or fees imposed under the Internal Revenue laws and other tax laws; W HEREAS, Section 133 (n) of R.A. 7160 clearly mandates that local Government Units Should not extend their taxing powers to cooperatives; NOW THEREFORE, BE IT ORDAINED BY THE PASAY CITY COUNCIL IN A SESSION DULY ASSEMBLED T H A T ; 1) Cooperatives duly registered under R.A. 6938 that transact business solely with its members be exempt from obtaining the Mayor’s Permit; 2) Duly registered Cooperatives which transact business with non-members are required to obtain the said Mayor’s Permit but are exempt from paying a corresponding fees to such permit; v 3) In the event that a legitimate cooperative which deals with both members and non - members whose accumulated reserves plus undivided \ savings have exceeded by more than Ten Million Pesos (P10,000.000.00) as provided by Section 62 Article V o f R.A. 6938, the exemption provided under this ordinance shall not apply. APPROVED in the City of Pasay This 1 4 th day o f October, in the year of Our Lord, nineteen hundred and ninety seven.Sponsored By : HON. GREG F. ALCERA W HEREAS, there are currently Seventy Five (75) legitimate Cooperatives which to the payment of fees imposed to these cooperatives by the Business Permit and License Office of the City Government; W HEREAS, Section 61 and 62 Art. V o f R .A 6938 otherwise known as the HON. W ENCESLAO B. TRINIDAD Acting City - Mayor.A LC ERA Act ; Presiding Officer page 2 o f ordinance exempting all legitimate cooperatives, registered and operating within the City o f Pasay from all taxes, fees and any dues imposed by the City Government. 1. HON ANTONEMO G. CALIXTO 2. HON. EMMANUEL M IBAY 3. HON JUSTO C. JUSTO 4 HON ROMULO M CABRERA 5. HON. REYNALDO O. PADUA 6. HON. ROBERTO L. ALVAREZ 7. HON. EDITA V VERGEL DE DIOS 8 HON. ULDARICO C. ARABIA 9. HON. ALBERTO V. PAREDES 10. HON. EDUARDO I AD VINCULA 11 HON. TEODULO R. LORCA JR. 12. HON. GENEROSO F. CUNETA 13 HON. LEVINE A. CUNETA ATTESTED BY: D R ANTONIO S. CO City Administrator | D12: Pasay | E12: 0.47402597 | F12: 56.7826
A13: 962 | B13: ORDINANCE ADOPTING THE COMPREHENSIVE LAND AND BUILDING USES PLAN FOR PASAY CITY | C13: i\ui vjjyju iv vy 1 l i i l r n iL iJ r f ii\ L 5 SANGGUNIANG PANLUNGSOD PASAYCITY ORDINANCE NO. qs? . S. 1997 ORDINANCE ADOPTING THE COMPREHENSIVE LAND AND BUILDING USES PLAN FOR PASAY CITY Sponsored by: Councilor ROM ULO M. CABRERA and Vice Mayor WENCESLAO B. TRINIDAD, Councilors GREG F. ALCERA, ANTONINO G. CALIXTO, EMMANUEL M. IBAY, JUSTO C. JUSTO, REYNALDO O. PADUA, ROBERTO L. ALVAREZ, EDITA V. VERGEL DE DIOS, ULDARICO C. ARABIA, ALBERTO V. PAREDES, EDUARDO I. ADVINCULA, TEODULO R. LORCA, JR., GENEROSO F. CUNETA and LEVINE A. CUNETA WHEREAS, Republic Act 7160, otherwise known as The Local Government Code of 1991 devolved to local government units the power to regulate the land and building uses in their respective areas of responsibilities. WHEREAS, consistent to the local anatomy and decentralization, the CITY PLANNING OFFICE of Pasay recommended to the SANGGUNIANG PANLUNGSOD a land and building uses scheme for Pasay City. WHEREAS, there is a need for adoption of a comprehensive land and uses plan for Pasay City to encourage the economic growth and prosperity, promote health ad safety, preserve and enrich culture, enhance balance ecology and preserve the convenience and comport of the City residents; c l WHEREAS, the SANGGUNIANG PANLUNGSOD is expressly empowered to -regulate the land and building uses through the enactment of zoning ordinance for an efficient and effective governance and the promotion of the general welfare of the y inhabitants; NOW THEREFORE, be it ORDAINED as it hereby ORDAINED, in session duly assembled, that: SECTION 1 . TITLE.* this ordinance shall be known as COMPREHENSIVE LAND AND BUILDING USES PLAN FOR PASAY CITY” .the “THE SECTION 2. PURPOSE.* This ordinance is enacted to promote the general welfare of the inhabitants, encourage and achieve the economic growth and prosperity, promote health and safety, preserve and enrich culture, enhance balance ecology and preserve the convenience and comfort of the City residents. SECTION 3. DECLARATION OF POLICY.* It is hereby declared the policy of the City to regulate the use of the land and building into different zones based on the nature, characteristics of its uses and environmental regulations as prepared by the City Planning Office. SECTION 4. ZONE CLASSIFICATION.- For the purpose of the land and building uses in the City, they are hereby divided into MAJOR and SPECIAL ZONES based on their predominant uses. The MAJOR ZONES shall be compromised of RESIDENTIAL, COMMERCIAL, INDUSTRIAL and PARKS while SPECIAL ZONES consist of INSTITUTIONAL, UTILITIES, CULTURAL, CEMETERY and PLANNED AREAS FOR DEVELOPMENT. (Ordinance No._ S-1997) COMMERCIAL ZONES are further divided into MINOR, MAJOR and METROPOLITAN Commercial Zones; Industrial Zones is characterized by mixed land and building uses of LIGHT and MEDIUM INDUSTRIAL AREAS; SECTION 5. RESIDENTIAL ZONE. - The following areas are declared LOW DENSITY RESIDENTIAL ZONES (R-l): Sec. 5-A.~ Doha Adela Hidalgo Village; Sec. 5-B.~ Airmen’s Village in Villamor Air Base, Pasay City; Sec. 5-C.~ Barangay 201, Pasay City, except those areas declared as COMMERCIAL areas; Sec. 5-D.- The entire NHA project in Maricaban, except those declared as COMMERCIAL ZONES; Sec. 5-E.- Don Carlos Village; Sec. 5-F.~ San Gregorio Village Sec. 5-G.- NAIA District, except those declared as Commercial and Utility Zones; Sec. 5-H.~ The entire NHA project in Sto. Nino, Barrio Pilipino, except those declared as COMMERCIAL zones; Sec. 5-1.- The area bounded by Edang Street, Apelo Cruz Street and Tripa de Gallina Creek, except those areas declared as COMMERCIAL areas, LIGHT and MEDIUM INDUSTRIAL zones; SECTION 6. RESIDENTIAL ZONES.- The following areas are declared combination of MEDIUM and HIGH DENSITY RESIDENTIAL ZONES (R-2 & R-3): Sec. 6-A. The areas bounded on the North by the boundary line of Pasay City and Manila; on the East by Tripa de Gallina; on the South by Gil Puyat avenue; (formerly Buendia Avenue); and on the West by the Service Road of Roxas Boulevard, Pasay City except one ( 1) lot deep, fronting and abutting the following streets and river, to wit: a. Gil Puyat avenue; b. Service Road of Roxas Boulevard; c. Harrison Street; d. Leveriza Street; e. Taft Avenue; f. Dominga Street; and g. Tripa de Gallina and those declared Special Zones; Sec. 6-B. The areas bounded on the North by Gil Puyat Avenue; on the East by Leveriza Street; on the South by Antonio Arnaiz Avenue (formerly Libertad Street); and on the West by Harrison Street, Pasay City, except those lots, one (1) lot deep, fronting and abutting the following, to wit: (Ordinance No._ S-1997) a. Gil Puyat Avenue; b. Leveriza Street; c. Antonio Arnaiz Avenue; and d. Harrison Street; and those declared Special Zones; Sec. 6-C. The areas bounded on the North by Gil Puyat Avenue; on the East by Tripa de Gallina, on the South by Amaiz Avenue; and on the west by Taft Avenue, Pasay City, except those lots, one (1) lot deep, fronting and abutting the following streets as river: a. Gil Puyat Avenue; b. Antonio Arnaiz Avenue; c. Padre Burgos Street; d. Taft Avenue; and e. Tripa de Gallina; and those declared Special Zones; Sec. 6-D. The areas bounded on the North by Antonio Amaiz Avenue; on the East by Tripa de Gallina; on the South by Efipanio De Los Santos Avenue (EDSA); and on the West by Harrison Street, Pasay City, except those lots, one (1) lot deep, fronting and abutting the following streets and river: a. Antonio Arnaiz Avenue; b. Taft Avenue; c. Padre Zamora Street; d. Protacio Street; e. EDS A; f. Harrison Street; and g. Tripa de Gallina; and those declared Special Zones; Sec. 6-E. The areas bounded on the North by Cuneta Avenue; on the East by Taft Avenue; on the South by the boundary line between Pasay City and Paranaque and on the West by Harrison Street, Pasay City, except those lots, one (1) lot deep, fronting and abutting the following streets: a. Taft Avenue; b. Cuneta Avenue; and c. Harrison Street; and those areas declared Special Zones in the said areas; Sec. 6-F. The area bounded on the North by EDSA; on the East by Aurora Boulevard; and on the South by Trip de Gallina and the West by Taft Avenue Extension, except those lots, one (1) lot deep, fronting and abutting the following streets: a. EDSA; b. Aurora Boulevard; and c. Taft Avenue; and those areas declared Special Zones; (■Ordinance No._ S-1997) 2):Sec. 6-G. The areas bounded on the North by EDSA; on the East by the boundary line between Pasay City and Makati City; on the South by Dilain Creek; and on the West by Tripa de Gallina, except those lots, ONE (1) lot deep, fronting and abutting the following streets and river; a. EDSA; b. C. Jose Street; c. P. Santos Street; and d. Tripa de Gallina; and those areas declared Industrial and Special Zones; SECTION 7. COMMERCIAL ZONES. - The following areas are declared: MINOR COMMERCIAL AREA (C -l) Sec. 7-A. All lots ONE (1) lot deep, fronting and abutting both sides of Protacio Street from Taft Avenue to the boundary line of PASAY CITY and MAKATI CITY; Sec. 7-B. All lots ONE (1) lot deep, fronting and abutting both sides of C. Jose to Tripa de Gallina; Sec. 7-C. All lots ONE (1) lot deep, fronting and abutting both sides of P. Santos Street, Malibay form EDSA to S . De Guzman Street; SECTION 8. The following areas are declared MAJOR COMMERCIAL AREA (C Sec.8-A. All lots ONE (1) lot deep, fronting and abutting both sides of F.B. Harrison Street from Gil Puyat Avenue to the boundary line of PASAY CITY and MANILA, except those declared as Institutional areas; Sec. 8-B. All lots ONE (1) lot deep, fronting and abutting the Eastern side of F.B. Harrison Street from A.Amaiz Avenue to Gil Puyat Avenue, except those declared as Institutional areas; Sec. 8-C. All lots ONE (1) lot deep, fronting and abutting both sides of F.B. Harrison Street from Gil Puyat Avenue to the boundary line of Pasay City and Paranaque to A. Amaiz Avenue, except those declared as Institutional areas; Sec. 8-D. All lots ONE (1) lot deep, fronting and abutting both sides of Taft Avenue from Gil Puyat Avenue to the boundary line of PASAY CITY and MANILA, except those declared as Institutional areas; Sec. 8-E. All lots ONE (1) lot deep, fronting and abutting both sides of Taft Avenue from Antonio Araniz Avenue to Gil Puyat Avenue, except those declared as Institutional areas; Sec. 8-F. All lots ONE (1) lot deep, fronting and abutting both sides of Taft Avenue from the boundary line of PASAY CITY and PARANAQUE to A. Amaiz Avenue; Sec. 8-G. All lots ONE (1) lot deep, fronting and abutting both sides of Leveriza Street from Gil Puyat Avenue to the boundary line of PASAY CITY and MANILA, except those declared as Institutional areas; *(Ordinance No. ______ , S-1997) Sec. 8-H. All lots ONE (1) lot deep, fronting and abutting Eastern side of Leveriza Street from A. Amaiz Avenue to Gil Puyat Avenue; Sec. 8-1. All lots ONE (1) lot deep, fronting and abutting both sides of Dominga Street from Gil Puyat Avenue to the boundary line of PASAY CITY and MANILA; Sec. 8-J . All lots ONE (1) lot deep, fronting and abutting both sides of P. Burgos Street from A. Amaiz Avenue to Gil Puyat Avenue, except those declared as Institutional areas; Sec. 8-K. All lots ONE (1) lot deep, fronting and abutting both sides of Zamora Street from EDSA to A. Arnaiz Avenue, except those declared as Institutional areas; Sec. 8.L. All lots ONE (1) lot deep, fronting and abutting both sides of Aurora Boulevard from Andrew Avenue to EDSA; Sec. 8.M. All lots FIFTEEN (15) meters deep strip, fronting and abutting both sides of Domestic Road from MIA Road To Andrew Avenue; Sec. 8-N. All lots FIFTEEN (15) meters deep strip, fronting and abutting both sides of MIA Road from the boundary line of PASAY CITY and PARANAQUE to Rotonda fronting Philippine Village Hotel except Nayong Pilipino; Sec. 8-0. All lots FIFTEEN (15) meters deep ship, fronting and abutting the Western side of NAIA Avenue from the boundary line of PASAY CITY and PARANAQUE to MIA Road; Sec. 8-P. All lots FIFTEEN (15) meters deep ship, fronting and abutting the Western side of South Super Highway from the boundary line of PASAY CITY and PARANAQUE to Nichols Toll Gate; Sec. 8-Q. All lots FIFTEEN (15) meters deep strip, fronting and abutting Merville Access Road in Barangay 201; Sec. 8-R. All lots ONE (1) lot deep strip, fronting and abutting both sides of Andrews Avenue from Pasay-Paraftaque Boundary to gate of Villamor Air Base. SECTION 9. The following areas are declared METROPOLITAN COMMERCIAL ZONE (C-3): Sec. 9-A. All lots ONE (1) lot deep strip, fronting and abutting the eastern side of the Service Road of Roxas Boulevard from Gil Puyat to the boundary line of PASAY CITY and MANILA; Sec. 9-B. All lots ONE (1) lot deep strip, fronting and abutting both sides of Gil Puyat Avenue from Roxas Boulevard to the boundary line of PASAY CITY and MAKATI; Sec. 9-C. All lots ONE (1) lot deep strip, fronting and abutting the both sides of A. Arnaiz Avenue from Roxas Boulevard to the boundary line of PASAY CITY and MAKATI; Sec. 9-D. All lots ONE (1) lot deep strip, fronting and abutting the both sides of EDSA from Roxas Boulevard to the boundary line of PASAY CITY and MAKATI; V *. ) v ^ ^ • / Sec. 9-E. The area bounded on the North by Gil Puyat Avenue, on the East by F.B. Harrison Street, on the South by the boundary line of PASAY CITY and PARANAQUE and the West by the Service Road of Roxas Boulevard, except those areas declared as Special Zones; Sec. 9-F. The area bounded on the North by Gil Puyat Avenue, on the East by Taft Avenue, on the South by A. Amaiz Avenue and on the West by Leveriza Street; and Sec. 9-G. The area bounded on the North by EDSA, on the East by Taft Avenue, on the South by Cuneta Avenue and on the West by F.B. Harrison Street; SECTION 10. INDUSTRIAL ZONE.- The following areas are declared: INDUSTRIAL/MEDIUM INDUSTRIAL ZONE: Sec. 10-A. All lots ONE (1) lot deep, fronting and abutting the level of Tripa de Gallina from Apelo Cruz to the boundary line of PASAY CITY and MANILA; Sec. 10-B. The areas bounded by the levee of Tripa de Gallina, EDSA, E . Rodriguez Street, Apelo Cruz and its Extension, the Boundary line of PASAY CITY and MAKATI, E . Flores Street, Vitales Street, E . Rodriguez Street, Maricaban Creek, and Tripa de Gallina, except those declared as Commercial and Institutional areas; SECTION 11. PARKS & RECREATIONAL ZONES.- The following areas are declared PARKS and RECREATIONAL ZONES: Sec. 11-A. The parklet between Luna Street and Taft Avenue near A. Amaiz street; Sec. 11-B. The Derham Park bounded on the North by Antonio Amaiz Avenue, on the West by the Auxiliary Road of Roxas Boulevard, on the East by F.B. Harrison Street and South by the property line of Sea Front; Sec. 11-C. The Malibay Plaza bounded by C. Jose Street and Apelo Cruz Extension, Malibay; Sec. 11-D. The area bounded by Andrews Avenue, 12th Street, Manlunas Street and 10th Street, Villamor Air Base; SECTION 12. INSTITUTIONAL ZONES.- All areas presently occupied by all existing institutions, private or government owned prior to the adoption of this zoning ordinance notwithstanding their location in other zone are declared INSTITUTIONAL ZONES; SECTION 13. UTILITY ZONE.- The areas occupied by the Board of Air Transportation, Domestics and Ninoy Aquino International Airports, except those areas therein that are declared, Residential, Commercial and Institutional areas, are declared as Utility Zone; SECTION 14. CULTURAL ZONES.- The areas occupied by the Cultural Center Tanghalang Francisco Balagtas (Folk Arts Theater), Philippine International Convention Center (PICC) at the reclamation area and the Nayong Pilipino in the NALA district are declared CULTURAL ZONES; well as those manufacturing products for regional consumption. Sec. 17-H. INSTITUTIONAL ZONES. - shall be characterized by governmental, and protective uses as well as institutional and characterized further by specialized governmental agencies providing institutional, protective, security and social services for the region or the country as a whole, and which are governed by specialized regulations, including mental hospitals, rehabilitations and training centers, military and secuxnty services. Sec. 17-1. PARKS AND RECREATION ZONES.- shall be characterized by parks facilities and amusements centers, resort establishments including marine and costal resorts, playgrounds, scenic areas and environmental conservation ad protection areas. Sec. 17-J. UTILITY AREAS.- Areas devoted to transport support facilities, such as bus/jeep terminals or stations, carbans, taxi stands, freight loading, storage, handling, unloading are, depot repair and maintenance facilities, piers, airports, train yards and other related facilities including communications infrastructure an other utilities. Sec. 17-K. CULTURAL AREAS.- Areas characterized by the presence of mixed institutional uses and structures that have contributed to the nation’s cultural heritage, and all such other uses which have historical significance in the community, such as museum, amphitheaters, old places and house, the preservation restoration of which is practical and desirable. Sec. 17-L. CEMETERY AREAS. - Consist of public graveyard and above-ground burial areas.and private Sec. 17-M. BLISS SITES.- Areas identified by the ministry of Human Settlements for its sites and services improvement program, characterized by high density housing, accessory uses and commercial support facilities. Sec. 17-N. PLANNED AREAS FOR DEVELOPMENT.- Consist of those areas identified by the Human Settlement Commission as areas for priority development and those areas indentified in Section 16-A and Section 16-B hereof. SECTION 18. ALLOWABLE LAND AND BUILDING USES.- No building, structure or land used and no building and structure shall be erected or altered in whole or in part except for one or more of the following: LOW DENSITY RESIDENTIAL ZONE A - PRINCIPAL USES 1. One family dwelling ; 2. Duplex type buildings; 3. Churches or similar places of worship and dwelling for the religious and seminaries; 4. Nursery and kindergarten schools, provided that they do not exceed two (2) classrooms; 5. Clubhouses, lodges and other social centers; 6. Parks, playgrounds, pocket parks, parkways, promenades and playlots; 7. Recreatinal uses such as tennis courts, basketball courts, swimming pools and similar uses operated by the government or private individuals as membership organizations for the benefit of their members, families or guests and not primarily for gain; 8. Townhouses. B - ACCESSORY USES 1. Uses customarily incidental to any of the aforemetioned uses located on the same lot, provided that such accessory uses shall not include any activity conducted for monetary gain or commercial purposes; a) Servants quarters; b) Home laundries; c) Non-commercial garages; d) Houses for pets such as dogs, birds, rabbits, and the like of not more than four square meters in floor area; e) Cottage or home industries such as embroidery, sewing, handicrafts, shell crafts, and thelike, condusted within a dwelling, provided that a maximum of 10 persons is employed and not more than 30% of the floor area of any one floor of the dwelling is devoted to such home occupation; provided further, that such home occupation does not require internal or external alterations, or involve construction features or use of equiptment not customary in dwelling. MIXED MEDIUM AND HIGH DENSITY RESIDENTIAL ZONE A-PRINCIPAL USES 1. One-family dwellings or more; 2. Duplex type buildings; 3. Town houses 4. Residential condominium or medium and high rise type; 5. apartment houses, apartelle, hometels; 6. Multi-family dwellings, accessories; 7. Boarding houses; 8. Tenements and mass housing; 9. Multi-storey apartment; 10. Churches or similar place of worship and dwellings for the religious and seminaries; 11. Public or private nursery, kindergarten and elementary and high schools provided theses will not exceed THIRTY (30) rooms; 12. Clubhouses, lodges and other social centers; 13. Parks, playground, pocket parks parkways promenade, playlots; 14. Recreational uses such as but not limited to golf courses, tennis courts, baseball diamonds, swimming pools and other sports and similar uses operated by the government or of private use and primarily go gain; 15. Clinics, family or industrial and exhibition areas; B * ACCESSORY USES.- Uses customarily incidental to any of the aforementioned principal uses such as servants quarter, home laundries, non commercial garages, house of pets, pump houses, small power plant, cottage or home industries such as embroidery, sewing, handicrafts, shell crafts conducted within a dwelling and occupy not more than 30% of any one floor of the dwelling, home offices of professionals, and incidental home occupants such as barbers and beauty shops, tailoring and dross shop neighborhood convenient store, retail drug store, offices with no actual display, sale, transfer, or handling of the office commodities in the premises, Barangay centers, pueroculture and health centers, police and fire stations, public utility structure necessary for the service of the area MINOR COMMERCIAL AREA.- only the following uses are permitted and allowed provided that the scale of operations must be a barangay zone size population to wit: 2) Pawnshops, photo and portrait studios, shoe shine and repair stands, photocopying shops, retail drug stores, tailoring and dross shops, backstop and bake 17 goods stores; 3) Personal service shops, such as but not limited to ware repair shops, laundries and Laundromats, repair shops of business machines household appliances and radio, television, electronic devices and all other small service establishments; 4) “Carinderia” , food stores, take home store, kiosks, ice cream parlors, soda fountain, coffee shop, deli shop, fruit stand, meat, fish and poultry stores, daily products, candies and other related good stores; 5) Gravel, sand, hallow blocks and other ornamental bricks dealers; 6) Furniture store, repair and upholstering jobs, printing and other small service establishments; 7) Blacksmith on barangay zone scale, tier and vulcanizing shops and welding shops; 8) Storage room incidental to the above uses; MAJOR COMMERCIAL AREAS (C-2).- Only the following uses a re permitted and allowed, provided the scale of the operations must be for City wide si populations, to wit:1) All uses allowed in residential zones; 1) All uses permitted in R-2, R-3 and and C-l areas; 2) Hardware and auto supply shops, auto sales, auto repair, car rentals, automotive handicraft, retail shops, accessory and spare shops and equipment and retails and sales yards; 3) Amusements centers, theaters, off-fronton stations, off-track stations commercial stables, dance halls or cabaret, dance and voice studios; 4. Restaurants, beer houses, canteens, delicatessen, confectionery shops and automates, soda fountain, groceries ad super clubs, night clubs and discotheques; 5) Hometels, inns and pension houses, motels reducing saloon, health studios, and massage and sauna parlors, tourist cabins and tourist homes; 6) General retail establishments such as curio or antique shops, pet shops and aquarium stores, book stores, art supplies and novelties, jewelry shops, liquor wine store and flower shops; 7) Sign and billboard shops, engraving and photo development shops, printing, blue printing and publishing shops; 8) Watch sales and service, locksmith and other related services; 9) Building material stores such as electrical and electronic stores; plumbing supply stores, ceramic, clay cement and other similar products; 10) Sporting goods, supplies, dry goods, stores, haberdasheries, ready­ made and knitted wear stores apparel, repair and other related repair services, and footwear shops; 11) Gasoline service and filling stations and commercial garage, multi storey structure; 12) Local wet and dry markets, including open markets (talipapa); 13) Supermarkets; 14) Machinery and machine shops, steel shops, machinery equipment supply and related wholesale trade, provided that the shops floor area shall not exceed 100 sq. mts. 15) Glassware and metalware shops, households equipment and appliance shops, electroplating shops, employment, news syndicate services, branch office, office equipment’s and repair shops; 16) Banks, savings/loan (related functions), money shops and other related financial institutions; 17) Other stores and shops for conducting retail business and local shopping establishments; 18) Funeral parlors, mortuaries and crematory services and mem chapels; 19) Messenger service, telephone and telegraphic exchange; 20) Institutional uses as elementary, high school, colleges universities, vocational and technical schools, general hospitals socialized general hospital, welfare and charitable institutions; * 21) Parking lots; 22) Radio and television broadcasting stations, and 23) Warehouses and storage facilities incidental to the above uses. METROPOLITAN COMMERCIAL AREA. - Only the following uses are permitted and allowed and the scale of operations include the outlying cities and municipalities: 1. All permitted uses in R~2, R-3, C~1 and C-2 areas; 2. Supermarkets, superstores, shopping and commercial centers; 3. Commercial recreation such as bars and nightclubs, boxing, wrestling, stadia, cinema, cockfighting arenas and racetracks, jai-alai; 4. Machinery equipment supply and related wholesale trade; 5. Radio-phonographs and records shops; 6. Musical instrument stores; 7. Printing, book binding shops, publishing shops and other related activities; 8. Lumber yards; 9. Institutional uses as university, complexes; 10. Commercial parking lots and garages; 11. Warehouses and storage facilities incidental to the above uses. MIXED LIGHT AND MEDIUM INDUSTRIAL AREAS 1. Manufacturing of human and animal food products and flavoring extracts; 2. Canning, preserving and processing fruits, juices, fish, crustaceans, meats and manufacture of vegetable, animal oils and fats; 3. slaughtering and meet dressing; 4. Distilling, rectifying and blending of spirits, liquor, wines, malt, softdrinks, carbonated water, beverages and syrups; 5. Ice plants and cold storage; 6. Milling rice, corn, flour and manufacturing of synthetic coffee from corn, rice and other cereals; 7. Spinning, waving and finishing textiles, hosieiy, carpets, rugs, manufacturing of linoleum (artificial leather), cordage, ropes, canvas and jute products; 8. Manufacturing of footwear, umbrellas, canes, brooms, fans, raincoats and other water proof garments, hats, ready to wear apparels and other accessories; 9. Manufacturing of tires, tubes and rubber products including recapping of tires; 10. Manufacturing and assembly plants of bicycles, motorcycles, automobiles, cars, buses, trucks trailers, motor engines and equipments, body and sidecar building, and repair thereof; 11. Manufacturing of wood, rattan and metal furnitures and fixtures and other products; 12. Manufacturing of clay products, pottery, china and earthware products, kitchen and table articles; 13. Manufacturing of tobaccos, cigar, cigarettes, chewing gum tobaccos, including curing, processing and redrying tobacco leaves; 14. Printing, publishing and other allied industries; 15. Fabricator of structural metal products, boilers, tanks and other structural and sheet metal, tins, cans, boxes, containers and other metal products and repair thereof; 16. Manufacturing of paints, varnishes, lacquers, shellac and stains; 17. Manufacturing of school and office supplies and other artists materials and athletic goods, except firearms; 18. Manufacturing and assembly plants for service industry machinery and household appliances and industrial apparatus and repair thereof; 19. Manufacturing of office, computing and accounting machines, radio, television and communication equipment and accessories and repair thereof. SECTION 19. BUILDING OR STRUCTURE USE. - No building, structure or land shall; hereafter be occupied or used and building and structure or part thereof shall be erected, constructed, moved or structurally altered except in conformity with the provisions of this ordinance; SECTION 20. YARD, OFF STREET PARKING SPACE. - No part of a road, off- street parking space, loading space, or other open space required of any building shall, for the purpose of complying with this ordinance, be included as part of the yard open space, off-street parking or loading space similarly required of any adjacent neighboring building. However, this shall not apply to building/s with common party walls or adjacent building lines, in which case, only the yard for free or non-abutting sides will be required; SECTION 21. TRAFFIC GENERATING BUILDING. - All traffic generating buildings and structures allowed in any of the areas must provide for adequate parking spaces for their employees, clients and visitors, where a person plans to establish a certain use/activity which will necessary affect the character of residential area in terms of traffic to be generated, the prior approval of the Barangay will have to be secured as one of the pre-requisite for location clearance and building permit. Furthermore it shall allocate an inner bay within its property for loading and unloading of passengers so that continues flow of traffic will not be obstructed; SECTION 22. HIGH RISE BUILDING. - All high rise buildings must strict omply with all the provisions of National Building Code and must provide its own ItVUJI) source of potable water in addition from the NAWASA, by putting up its own deepwell, which should not be less than ONE HUNDRED FEET (100) feet deep and should not be ess than THIRTY (30) feet away from any sewerage lines and septic tanks; SECTION 23. ADVERTISING AND BUSINESS SIGNS. - Advertising and business signs to be displayed or put up for public view in any of the areas herein enumerated must comply with existing laws, rules and regulations and shall not be allowed along scenic parks, recreation areas and the shoreline of the Manila Bay; SECTION 24. DWELLING ON REAL LOTS. - No building used or intended to be used as residence shall be allowed in any rear lot unless such lot has a right of way easement of at least THREE (3) meters leading to the street; SECTION 25. STRUCTURE TO HAVE ACCESS. - Every building hereafter erected or moved shall have access to a public street or to a private street open to the public and all structures shall be so located on lots so as to provide safe and convenient access for servicing fire protection units; SECTION 26. YARD REQUIREMENTS ALONG A DISTRICT BOUNDARY LINE. - Lots abutting on a zone boundary line shall conform to the yard requirements of the more restrictive zone boundary by the line; SECTION 27. DWELLING GROUP. - When it is impractical to apply the requirements of these zoning regulations to individual building unit in a residential compound, consisting of a two or more buildings, a permit for the construction of such compound may be issued, provided that the plan thereof conform to the following conditions: Sec. 27-A. That the building are to be used only for residential purposes and such uses are permitted in the zone where the compound is located; Sec. 27-B. That the average lot area per familym, of dwelling unit in the compound, exclusive of the area used or to be used for streets or driveways, is not less than the lot area per family required in the district; Sec. 27-C. That there is provided within the tract on which the residential compound is to be located, an open space for playground purposes with an area equivalent to at lest an aggregate area of five (5%) percent of the required lot area per family, but in no case less than one hundred square meters; provided that where the residential compound is intended for less than ten families, the setting aside of such area for playground purposes may be dispensed with; and provided further, that an open space may be used as part of the yard requirements for the compound; and Sec. 27-D. That there is provided within the tract on which the residential compound is to be erected or immediately adjacent thereto, an adequate private garage or off-street parking area, depending on the needs of the residents and their visitors. i SECTION 28. HEIGHT REGULATION. Sec. 28-A. Where as residential area adjoins a C2 district without an intervening street or permanent open spaces over 6 meters in width, and where zoning lots separated by area rW T T T boundaries have adjacent front yards, the proposed structure fronting the residential area shall be limited to a height of 12 meters of four-storey building whichever is lesser; Sec. 28-B. Where an R2 district adjoins a C2 or C3 area without a intervening street or permanent open spaces over 3 meters in width, the proposed structure of C2 or C3 district adjacent to R2 zone shall be limited to a height of 9 meters or three-storey building whichever is lesser; Sec. 28-C. Where an R2 or R3 area adjoins an 1-1 or 1-2 zone without an intervening street or permanent open spaces over EIGHT meters in width, the proposed industrial structure fronting the residential zone shall be limited to a height equivalent to 9 meters or three-storey building whichever is lower; Sec. 28-D. Structures adjacent to airports must comply with the building heights set by the Board of Air Transportation. SECTION 29. PERFORMANCE STANDARDS. - All land uses, developments or constructions shall conform to the following standards: Sec. 29-A. Noise and Vibration. - All noise and vibration producing machinery shall be enclosed by a building and shall be provided with effective, noise absorbing materials, noise silencers and mufflers, and an open yard of a distance of not less than twenty ( 20) meters from the street or adjoining property lines and property planted to dense trees and buffers. To minimize vibration, a machinery should be mounted on a shock absorbing mountings, such as cork set on set reinforced concrete foundations or a floating isolated foundation set on piles, as needed by the machinery concerned, to reduce all noise and vibration to a reasonable minimum. Noise which is objectionable due to intermittence beat frequency or high pitch shall not be allowed unless enclosed in sound proof buildings as tested and approved | D13: Pasay | E13: 0.47402597 | F13: 56.7826
A14: 961 | B14: AN ORDINANCE DECLARING SEPTEMBER 27, 1997 AS THE "NEW GENERATIONS CONFERENCE DAY". | C14: REPUBLIC OF THE PHILIPPINES OFFICE OF THE SANGGUNIANG PANLUNGSOD PASAY CITY, METRO MANILA ORDINANCE NO. 967 S-1997 AN ORDINANCE DECLARING SEPTEMBER 27, 1997 AS THE “NEW NERATIONS CONFERENCE DAY”. SPONSORED BY: COUNCILOR GREG F. ALCERA WHEREAS, the Joint Efforts of Pasay Rotary Clubs (JEPROCS) have lined up a number of community and vocational oriented projects in order to promote and enhance the skills and talents of the youth thus planning to create a forum dubbed as Rotary New Generation Conference Day '97; WHEREAS, their very objective is to promote clean and healthful living, provide skills training to indigent out of school youth and to recognize the outstanding contributions of the citizenry like teachers, policemen and other public servants in supporting the young people in Pasay City; WHEREAS, the youth as we believe to be, as said by Dr. Jose Rizal are the future hope and leaders of the country; WHEREAS, there is a need for different sectors of the society to directly participate and contribute with one another their various visions or thought that could identify the necessity of the youth in the said forum. - NOW THEREFORE, BE IT ORDAINED AS IT IS HEREBY ORDAINED, by the Sangguniang Panlungsod of Pasay in session duly assembled to declare as it hereby declares September 27, 1997 as the “NEW GENERATIONS CONFERENCE DAY”. Enacted this 7 day of October in the Year of Our Lord Nineteen Hundred and Ninety Seven. APPROVED ; Lf es LM HON. WENCESLAO B. TRINIDAD HON. GREG F/. ALCERA Acting City Mayor Acting VAce Mayor J 1. HON. ANTONINO G. CALIXTO. 7 Maa ae, Ss 2. HON. EMMANUEL M. IBAY - shill, "ln * 3. HON. JUSTO C. JUSTO CORY gill A 4 Ordi 61,S- claring September 27, 1997 as _ the “New Generations Conference Day”. 4. HON. ROMULO M. CABRERA Vy 5. HON. REYNALDO O. PADUA Ml —_ yr 6. HON. ROBERTO L. ALVAREZ Y—_ : 7. HON. EDITA V. VERGEL DE DIOS hy Pr 8. HON. ULDARICO C. ARABIA 9. HON. ALBERTO V. PAREDES 10. HON. EDUARDO I. ADVINCULA ay , 7 7, 11. HON. TEODULO R. LORCA, JR. _——-$* 7 L/L a Gis was ANS NAN « ATTY. a City Secretary wo 12. HON GENEROSO F. CUNETA 13. HON. LEVINE A. CUNETA | D14: Pasay | E14: 0.47402597 | F14: 56.7826
... A122: 6074 | B122: AN ORDINANCE DONATING THE AMOUNT OF TWO MILLION FIVE HUNDRED THOUSAND PESOS (PHP2,500,000.00) TO BE TAKEN FROM AN UNOBLIGATED BALANCE OF APPROPRIATIONS UNDER THE OFFICE OF THE CITY MAYOR EXECUTIVE BUDGET CY 2020 - SPECIAL PURPOSE APPROPRIATION 5% LOCAL DISASTER RISK REDUCTION MANAGEMENT FUND (LDRRMF) - QUICK RESPONSE FUND WITH ACCOUNT CODE NO. 5-02-99-080 TO BE DONATED TO THE HEREUNDER MUNICIPALITIES OF THE PROVINCE OCCIDENTAL MINDORO ADVERSELY AFFECTED BY TYPHOON "URSULA" LAST DECEMBER 25, 2019 THAT CAUSED MAJOR DESTRUCTION IN INFRASTRUCTURE, AGRICULTURAL PRODUCTION, PROPERTIES AND DISRUPTION IN RESOURCES OF LIVELIHOOD SUBJECT TO ALL ACCOUNTING, AUDITING AND LEGAL RULES AND REGULATIONS ON THE MATTER | C122: Republic of the Philippines SANGGUNIANG PANLUNGSOD Pasay City, Metro Manila PA pln ORDINANCE NO. 6074 S-2020 AN ORDINANCE DONATING THE AMOUNT OF TWO MILLION FIVE HUNDRED THOUSAND PESOS (PHP2,500,000.00) TO BE TAKEN FROM AN UNOBLIGATED BALANCE OF APPROPRIATIONS UNDER THE OFFICE OF THE CITY MAYOR EXECUTIVE BUDGET CY 2020 —- SPECIAL PURPOSE APPROPRIATION - 5% LOCAL DISASTER RISK REDUCTION MANAGEMENT FUND (LDRRMF) - QUICK RESPONSE FUND WITH ACCOUNT CODE NO. 5-02-99-080 TO BE DONATED TO THE HEREUNDER MUNICIPALITIES OF THE PROVINCE OCCIDENTAL MINDORO ADVERSELY LN AFFECTED BY TYPHOON “URSULA” LAST DECEMBER 25, 2019 THAT CAUSED MAJOR DESTRUCTION IN INFRASTRUCTURE, AGRICULTURAL PRODUCTION, PROPERTIES AND DISRUPTION IN RESOURCES OF LIVELIHOOD SUBJECT TO ALL ACCOUNTING, AUDITING AND LEGAL RULES AND REGULATIONS ON THE MATTER ee ~ SPONSORED BY MEMBERS OF THE SANGGUNIANG PANLUNGSOD Ni , Ay WHEREAS, thru the representation of the Congresswoman of Occidental Mindoro, Hon. Josephine Y. Ramirez-Sato, the city government of Pasay is requesting from the Sangguniang Panlungsod to provide cash assistance to <4 several municipalities of Occidental Mindoro due to typhoon “ Ursula” last December 25, 2019 that cause major destruction in infrastructure, agricultural production, properties and disruption in resources of livelihood. NOW, THEREFORE BE IT ORDAINED AS IT IS HEREBY ORDAINED by the Sangguniang Panlungsod in session duly assembled that: SECTION 1. APPROPRIATION. - The sum of TWO MILLION FIVE HUNDRED THOUSAND PESOS (PHP2,500,000.00) is hereby appropriated to be taken from an unobligated balance of appropriations under the Office of the City Mayor Executive Budget CY 2020 - Special Purpose Appropriation - 5% Local Disaster Risk Reduction Management Fund (LDRRMF) - Quick Response Fund with account code no. 5-02-99-080 to be donated to the following Municipalities of Province of Occidental Mindoro, to wit: tof pe PAGE 2 OF PAGE 3 OF “AN ORDINANCE DONATING THE AMOUNT OF TWO MILLION FIVE HUNDRED THOUSAND PESOS (PHP2,500,000.00) TO BE TAKEN FROM AN UNOBLIGATED BALANCE OF APPROPRIATIONS UNDER THE OFFICE OF THE CITY MAYOR EXECUTIVE BUDGET CY 2020 - SPECIAL PURPOSE APPROPRIATION - 5% LOCAL DISASTER RISK REDUCTION MANAGEMENT FUND (LDRRMF) - QUICK RESPONSE FUND WITH ACCOUNT CODE NO. 5-02-99-080 TO BE DONATED TO THE HEREUNDER MUNICIPALITIES OF THE PROVINCE OCCIDENTAL MINDORO ADVERSELY AFFECTED BY TYPHOON “URSULA” LAST DECEMBER 25, 2019 THAT CAUSED MAJOR DESTRUCTION IN INFRASTRUCTURE, AGRICULTURAL a ee ‘ : PRODUCTION, PROPERTIES AND DISRUPTION IN RESOURCES OF LIVELIHOOD SUBJECT TO ALL ACCOUNTING, AUDITING AND LEGAL RULES AND REGULATIONS ON THE MATTER”. SECTION 2. REQUIREMENT OF ACCOUNTING AND AUDITING. - All appropriations shall be subjected to necessary accounting and auditing rules and procedures. SECTION 3. EFFECTIVITY. — This Ordinance shall take effect after the passage by the Sangguniang Panlungsod, approval by the City Mayor and one (1) day after posting in three (3) conspicuous places in the City of Pasay _ | MUNICIPALITY, | AMOUNT pe ee ee Oe 2 200 G00" | J = § ORDAINED in the City of Pasay, Philippines this 6 day of January in the Year of Our Lord, Two Thousand Twenty CERTIFIED APPROVED BY THE SANGGUNIANG PANLUNGSOD: District-I Hon. MARK ANTHONY A. CALIXTO City Councilor Hon. MARY GRACE B. SANTOS City Councilor Hon. MA. ANTONIA C. CUNETA City Councilor pe 6 orem Hon. ABRAHAM ALBERT Q. ALVINA City Councilor ——— Hon. MARLON A. PESEBRE City Councilor Tang District-II \— -: Hon. ALLAN T. PANALIGAN City Covincilor Hon. DONNABEL M. VENDIVEL City C Hon. ARNEL sas ' weak C. ISIDRO, City Councilor Hon. EDITHA Y. GUERRA City Councilor PAGE 3 OF PAGE 3 OF “AN ORDINANCE DONATING THE AMOUNT OF TWO MILLION FIVE HUNDRED THOUSAND PESOS (PHP2,500,000.00) TO BE TAKEN FROM AN UNOBLIGATED BALANCE OF APPROPRIATIONS UNDER THE OFFICE OF THE CITY MAYOR EXECUTIVE BUDGET CY 2020 - SPECIAL PURPOSE APPROPRIATION - 5% LOCAL DISASTER RISK REDUCTION MANAGEMENT FUND (LDRRMF) - QUICK RESPONSE FUND WITH ACCOUNT CODE NO. 5-02-99-080 TO BE DONATED TO THE HEREUNDER MUNICIPALITIES OF THE PROVINCE OCCIDENTAL MINDORO ADVERSELY AFFECTED BY TYPHOON “URSULA” LAST DECEMBER 25, 2019 THAT CAUSED MAJOR DESTRUCTION IN INFRASTRUCTURE, AGRICULTURAL PRODUCTION, PROPERTIES AND DISRUPTION IN RESOURCES OF LIVELIHOOD SUBJECT TO ALL ACCOUNTING, AUDITING AND LEGAL RULES AND REGULATIONS ON THE MATTER”. L,La— Hon. RICARDO E. SANTOS Hon. AILEEN C. PADUA City Councilor City Councilor EX-OFFICIO MEMBERS Hon. JULIE G. GONZALES Hon. JOSE MIGUEL A. MANEZ President President Liga ng mga Barangay SK Federation Pasay City Chapter Pasay City Chapter Certified True Copy: \ DR. VOLT E F. PORTUGUEZ Officer-In-Charge Office of the Secretary to the Sangguniang Panlungsod Attested by: —fpety #. ACL o7—_ Hon. NOEL L. DEL ROSARIO | City Vice Mayor & Presiding Officer Approved: ao (- Hon. IMELDA CALIXTQ RUBIANO = City a chal > ———.. | D122: Pasay | E122: 0.47402597 | F122: 56.7826
A123: 6072 | B123: AN ORDINANCE PROVIDING FOR A CENTRALIZE ISSUANCE OF BARANGAY CLEARANCES FOR PERMITS RELATED TO DOING BUSINESS IN BEHALF OF ANY OF THE 201 BARANGAYS IN THE CITY OF PASAY, AUTHORIZING THE LOCAL GOVERNMENT UNIT CONCERNED TO COLLECT THE PAYMENT OF REASONABLE FEES THEREFORE AND THE REMITTANCE OF THE BARANGAY'S SHARE IN THE COLLECTIONS IN CONFORMITY WITH SECTION 10, RULE IX OF JOINT MEMORANDUM CIRCULAR NO. 2019-001, SERIES OF 2019 ENTITLED IMPLEMENTING RULES AND REGULATIONS OF REPUBLIC ACT NO. 11032 OTHERWISE KNOWN AS THE "EASE OF DOING BUSINESS AND EFFICIENT GOVERNMENT SERVICE DELIVERY ACT OF 2018" SUBJECT TO APPLICABLE LAWS, RULES AND REGULATIONS ON THE MATTER. | D123: Pasay | E123: 0.47402597 | F123: 56.7826
A124: 6070 | B124: AN ORDINANCE GRANTING EXEMPLARY MOTIVATION INCENTIVE (EMI) TO QUALIFIED CITY EMPLOYEES AND OFFICIALS OF THE CITY GOVERNMENT OF PASAY, METRO MANILA | C124: AF Republic of the Philippines SANGGUNIANG PANLUNGSOD Pasay City Ordinance No. 6070, S-2019 GO R Di 1t N A N € E AN ORDINANCE GRANTING EXEMPLARY MOTIVATION INCENTIVE (EMI) TO QUALIFIED CITY EMPLOYEES AND OFFICIALS OF THE CITY GOVERNMENT OF PASAY, METRO MANILA Sponsored by Vice Mayor NOEL L. DEL ROSARIO Co-sponsored by City Councilors MARK ANTHONY A. CALIXTO, ALLAN T.S PANALIGAN, MARY GRACE B. SANTOS, DONNABEL M. VENDIVEL, MA. ANTONIA C. CUNETA, ARNEL REGINO T. ARCEO, ABRAHAM ALBERT Q. ALVINA, JOSE C. ISIDRO, JR., MARLON A. PESEBRE, EDITHA Y. MANGUERRA, RICARDO E. SANTOS, AILEEN C. PADUA, JULIE G. GONZALES and JOSE MIGUEL A. MANEZ WHEREAS, the City of Pasay has been awarded consistently for four (4) consecutive years from CY 2016-2019 the Seal of Good Local Governance (SGLG) from the Department of Interior and Local Government (DILG); WHEREAS, the City of Pasay has been conferred as the Regional Winner of the Seal of Child-Friendly Local Governance (SCFLG) for 2018 Audit and a Finalist for Presidential Award for Child-Friendly City this November 29, 2019; WHEREAS, the City of Pasay is also a Silver Awardee for 2018 CADAC Audit, 1* Place in the Local Peace and Order Council Performance Audit (POC) 2018, 2™ Place in the Local Peace and Order Council Performance Audit (POC) 2019 and MBCRP Passer; WHEREAS, tthe City of Pasay of Pasay also received various awards from the Cities & Municipalities Competitiveness Index (CMCI), to wit: CY 2018 - 1 Place — Government Efficiency 2"! Place — Economic Dynamism 3" Place — Overall CY 2019 - 1“ Place ~ Economic Dynamism WHEREAS, the City recognizes valuable role of all employees and officials in its continuous progress and growth, and hereby recognizes, appreciates and rewards their hard work and good governance by granting them an Exemplary Motivation Incentive (EMI) to be considered as other personnel benefits; WHEREAS, the Supreme Court has upheld the power of Local Government Units (LGUs) to grant additional. allowances and benefits to their officials and employees citing the “state policy of local autonomy” as guaranteed by the 1987 Constitution under Section 25, Article II, and Section 2, Article X, as well as the Local Government Code of 1991. NOW THEREFORE, BE IT ORDAINED AS IT IS HEREBY ORDAINED, by the Sangguniang Panlungsod of the City of Pasay, Metro Manila, in a session assembled that: — o a FC * Page 2 of Ordinance No.6070, $-2019 TF Section 1. All officials, regular and casual employees and staff of the City Government of Pasay City, Metro Manila, hired as of October 31, 2019 shall be entitled to Exemplary Motivation Incentive (EMI) equivalent to 99.8% of their basic salaries subject to the provisions of Sections 2 & 3 hereof; Section 2. The City Government employees and staff who are qualified to receive Exemplary Motivation Incentive (EMI) are the following: a) Those who rendered at least a total of an aggregate of four (4) months of service including leave of absence with pay as of October 31, 2019; b) Those who have rendered less than four (4) months of service, but subject to the limitations imposed by Section 3 hereof; c) Personnel who are formally charged with administrative and/or criminal cases which are still pending for resolution may be entitled to Exemplary Motivation Incentive (EMI) until found guilty and meted penalty, subject to item (d) hereof; d) Personnel found guilty and meted penalty shall NOT be entitled to Exemplary Motivation Incentive (EMI) in the year the decision was handed down. He/She shall refund any Exemplary Motivation Incentive (EMI) received that year; e) Government personnel who are no longer in the service starting November 1, 2019 shall not be entitled to Exemplary Motivation Incentive (EMI). BOR PR Section 3. Government personnel who have rendered less than four (4) months o service as of October 31, 2019 shall be entitled to a pro-rated Exemplary Motivation Incentive (EMI), as follows: Section 4. The Sangguniang Panlungsod authorized the City Mayor to utilize savings from salaries of casuals and contractual, PERA, hazard pay, year end bonus, cash gift and mid- year bonys from January 1 to October 30, 2019 to realigbn/augment the ether persenal benefit }///Account Code No. 5-01; . oe as other personnel benefit for this purpose. Tl ees ection 5. The City Treasurer shall set aside the necessary funds to cover the Exemplary Motivation Incentive (EMI) and disburse the same subject to usual accounting and auditing procedures and further, subject to availability of funds. Section 6. The authority, issuance and approval hereof shall be subject to compliance with existing laws and COA rules and regulations on appropriations, expenditures and procurement. Section 7. Repealing Clause. - The provisions of existing ordinances, executive orders and other issuances or portion thereof which are inconsistent herewith are hereby repealed, modified and amended. Section 8. Separability Clause. — If any part or provisions of this Ordinance be held : unconstitutional or invalid, other parts of provisions hereof which are not affected thereby shall ; | continue in full force and effect. Section 9. fectivity. — This ordinance shall take effect upon passage by the Sangguniang P , approval by the City Mayor and posting in three (3) conspicuous places in Pasay y _ Page 3 of Ordinance Np.6070, S-2019 ORDAINED in the City of Pasay, Metro Manila, Philippines, this 25" day of November, in the Year of Our Lord, Two Thousand Nineteen. District- I Hon. MARK ANTHONY A. CALIXTO City Goungilor Hon. MARY GRACE B. SANTOS i uncilor Hon. . XNTONIA C. CUNETA City Councilor Hon. soeJom were Q. ALVINA City Councilor eoOoeOSe Se __ Hon. MARLON A. PESEBRE Ci pra Hon. RICCARDO E. SANTOS Hon. AILEEN C. PADUA ity Councilor City Councilor Ex-Officio Members rie eee ONZALES Hon. JOSE MIGUEL A. MANEZ President President Liga ng mga Barangay Sangguniang Kabataan Federation Pasay City Chapter Pasay City Chapter Certified True ATTY ZKOB O B. YAM Ci cretary Attested by: Hon. NOEL L. DEL ROSARIO City Vice-Mayor & Presiding Officer weg ee aa O City Mayor | D124: Pasay | E124: 0.47402597 | F124: 56.7826
A125: 6069 | B125: AN ORDINANCE ADOPTING THE CITIZEN'S CHARTER OF THE CITY GOVERNMENT OF PASAY PURSUANT TO REPUBLIC ACT NO. 11032, OTHERWISE KNOWN AS THE EASE OF DOING BUSINESS AND EFFICIENT GOVERNMENT SERVICE DELIVERY ACT OF 2018 | C125: Republic of the Philippines SANGGUNIANG PANLUNGSOD Pasay City Ordinance No 6869 , 89-2019 GO Rk D i! N A N € EE AN ORDINANCE ADOPTING THE CITIZEN’S CHARTER OF THE CITY GOVERNMENT OF PASAY PURSUANT TO REPUBLIC ACT NO. 11032, OTHERWISE KNOWN AS THE EASE OF DOING BUSINESS ANDEFFICIENT GOVERNMENT SERVICE DELIVERY ACT OF 2018 Sponsored by MEMBERS OF THE SANGGUNIANG PANLUNGSOD WHEREAS, as stated in Article II, Section 27 of the 1987 Constitution, the state shall maintain honesty and integrity in the public service and shall take positive and effective measures against graft and corruption; WHEREAS, the Ease of Doing Business and Efficient Government Service Delivery Act of 2018, declares as the policy of the State to promote integrity, accountability, proper Pd management of public affairs and public property as well as to establish effective practices, aimed at efficient turnaround of the delivery of government services and the prevention of graft and corruption in government. Towards this end, the State shall take appropriate measures to promote transparency in each agency with regard to the manner of transacting with public, which shall encompass a program for the adoption of simplified requirements and procedures that will reduce red tape and expedite business and non-business related transactions in government; WHEREAS, Sec. 6 of R.A. 11032 mandates all government agencies including departments, bureaus, offices, instrumentalities, or government-owned and/or controlled corporations, or LGUs to set up their respective most current and updated service standards to be known as the Citizen’s Charter in the form of information billboards which shall be posted at the main entrance of offices or at the most conspicuous place, in their respective websites and in the form of published materials written in English, Filipino, or in the local dialect, that detail a) A comprehensive and uniform checklist of requirements for each type of application or request; b) The procedure to obtain a particular service; c) The person/s responsible for each step; d) The maximum time to conclude the process; e) The document’s to be presented by the applicant or requesting party, if | necessary; f) The amount of fees, if necessary, and g) The procedure for filing complaints. ‘I WHEREAS, through the establishment of this Citizen’s Charter, services to the ‘e constituents of Pasay City will be enhanced and other advantages are expected to follow, such as less cost of public service delivery, reduce vulnerability to graft and corruption, availability of NY feedback mechanism, existence of basis for assessing the performance of the local government and staff, as well as customer satisfaction, equal treatment of customers, availability of Ww complaints and redress mechanism, and opening of the opportunity for people participation on service improvement, among others. 6 NOW THEREFORE, BE IT ORDAINED AS IT IS HEREBY ORDAINED by the SanggunggawPanlungsod in session duly assembled: t ' 6069 ° Page 2 of Ordinance No. Section 1. Short Title. — This ordinance shall be known as the “Citizen’s Charter of the City Government of Pasay”. Section 2. Policy. — It is hereby declared the policy of this City to promote integrity and accountability of its public officials and employees and exercise transparency in the manner of transacting business with the general public by minimizing red tape and prevent graft and corruption. Section 3. Coverage. — This ordinance shall apply to all officials and employees of each department or office of the City Government of Pasay whether providing business or non- business transactions to the general public. Section 4. Citizen’s Charter. — The City Government of Pasay hereby adopts its Citizen’s Charter pursuant to Republic Act No. 11032 which shall form and made an integral part of this Ordinance. Section 5. Dissemination. — The City Government shall be responsible for the dissemination and introduction of the Citizen’s Charter to all the constituents and stakeholders in the locality. Section 6. Review. — The Citizen’s Charter shall be reviewed every three (3) years for any improvement, inclusion, amendment or update its provisions. Section 7. Penalty Clause. — Any person who violates any provision of this ordinance shall be prosecuted against in accordance with the penalties imposed by Republic Act No. 11032 otherwise known as the Ease of Doing Business and Efficient Government Service Delivery Act of 2018. Section 8. Separability Clause. — If for any reason or reasons, any part of this Ordinance is held unconstitutional or invalid, other parts or provisions hereof that are not affected shall continue to be in full force and effect. Section 2. Effectivity. — This ordinance shall take effect upon passage by the Sangguniang Panlungsod, approval by the City Mayor, and one (1) day after posting in three (3) conspicuous places in the City of Pasay. ORDAINED in the City of Pasay, Metro Manila, Philippines, this ©3t® day of November, in the Year of Our Lord, Two Thousand Nineteen. CERTIFIED APPROVED BY THE SANGGUNIANG PANLUNGSOD District- I t- I he Hon. MARK ANTHONY A. CALIXTO Hon. Aj T. PANALIGAN City Councilor Wty Councilor Hon. MARY GRACE B. SANTOS Hon. DONNABEL M. VENDIVEL City Councilor City’C@uncilor Hon. MA. AN IA C. CUNETA Hon. ARNEL City Councilor City ee S-2019 AT * - , . ‘ | Page 3 of Ordinance No. 6069 S-2019 Hon. ABRAHAM ALBERT Q. ALVINA Sfxé C. ISIDRO, JR. City Councilor City Counci a bh) J Hon. MARLON A. PESEBRE Hon. EDITHA Y. MANGU City Councilor City Cguncilor ——— Hon. RICARDO E. SANTOS Hon. AILEEN C. PADUA City Councilor City Councilor Ex-Officio Members Hon. ee GONZALES Hon. JOSE MIGUEL A. MANEZ President President Liga ng mga Barangay Sangguniang Kabataan Federation Pasay City Chapter Pasay City Chapter Certified True Copy: ~ ROBERTO B. YAM Cyy Secretary AT Attested by: Hon. NOEL L. DEL ROSARIO City Vice-Mayor & Presiding Officer “eS { ye HON-IMELDA CALIXTO-RUBIANO City Mayor | D125: Pasay | E125: 0.47402597 | F125: 56.7826
A126: 6066 | B126: AN ORDINANCE AMENDING SUB-PARAGRAPH (II), PARAGRAPH (B), SECTION 1, CHAPTER 8 OF ORDINANCE NO. 5745, S-2016 ON THE MATTER OF AMUSEMENT TAX TO BE PAID ON MUSICAL CONCERTS, THEATRIC PLAYS, FASHION SHOWS AND OTHER LIVE PERFORMANCES AT THE ASTRODOME/ARENA OR OTHER HALLS OR PLACES PRESENTED BY FOREIGN ARTISTS FROM TEN PERCENT (10%) TO FIVE PERCENT (5%) | C126: li r Republic of the Philippines SANGGUNIANG PANLUNGSOD Pasay City Ordinance No. ©9%6 , 89-2019 O R D I N A N CE wz —— — —— —— AN ORDINANCE AMENDING SUB-PARAGRAPH (ii), PARAGRAPH (b), , SECTION 1, CHAPTER 8 OF ORDINANCE NO. 5745, S-2016 ON THE MATTER OF AMUSEMENT TAX TO BE PAID ON MUSICAL CONCERTS, THEATRIC PLAYS, FASHION SHOWS AND OTHER LIVE PERFORMANCES AT THE ASTRODOME/ARENA OR OTHER HALLS OR PLACES PRESENTED BY FOREIGN ARTISTS FROM TEN PERCENT (10%) TO FIVE PERCENT (5%) ee, eee ee ee Se ee eee Be it enacted by the Sangguniang Panlungsod in session duly assembled: \ Section 1. Amendment On The Payment Of Amusement Tax. — The pertinent NG provision of sub-paragraph (ii), paragraph (b), Section 1, Chapter 8 of Ordinance No. 5745, S-2016 on the matter of amusement tax to be paid on musical concerts, theatric plays, fashion shows and other live performances at the astrodome/arena or other halls or places presented by foreign artists is hereby amended from ten percent (10%) to five percent (5%). Section 2. Effectivity. — This ordinance shall take effect upon passage by the Sangguniang Panlungsod, approval by the City Mayor, posting in three (3) conspicuous places in the city and publication once in a newspaper of general circulation in the local government unit concerned. ORDAINED in the City of Pasay, Metro Manila, Philippines, this 18th day of November, in the Year of Our Lord, Two Thousand Nineteen. District- I WW T. PANALIGAN Hon. MARK ANTHONY A. CALIXTO Hon. Ae aay A Councilor City Councilor Hon. MARY GRACE B. SANTOS Hon. DONNABEL M. VENDIVEL j City Councilor City Councilor Kr — err 6066 | * . Page Z of Ordinance No. 6 S-2019 Hon. MA. ANTONIA C. CUNETA City Councilor a Hon. ABRAHAM ALBERT Q. ALVINA City Councilor —oeseSEe ee -- — Hon. MARLON A. PESEBRE City Councilor ) Hon. RIC O E. SANTOS City Councilor Hon. JOSE C. ISIDRO, JR. City Councilor Hon. AILEEN C. PADUA City Councilor Ex-Officio Members Hon. niitéd¢ NZALES President Liga ng mga Barangay Pasay City Chapter Attested by: TDUpnl. 6.4AC Ke — Hon. NOEL L. DEL ROSARIO City Vice-Mayor & Presiding Officer Approved: L HON. IMELDA CALIXTO-RUBIANO 4. ~City Mayor Hon. JOSE MIGUEL A. MANEZ President Sangguniang Kabataan Federation Pasay City Chapter Certified True Copy: ATTY. ERO B. YAM | D126: Pasay | E126: 0.47402597 | F126: 56.7826
A127: 6064 | B127: AN ORDINANCE PROVIDING FOR THE BASIC QUALIFICATIONS/CRITERIA FOR FINANCIAL ASSISTANCE FOR THOSE INDIVIDUALS AVAILING OF SCHOLARSHIP GRANTS AND FINANCIAL ASSISTANCE TO HIGH SCHOOL AND COLLEGE STUDENTS IN PUBLIC AND PRIVATE COLLEGES AND UNIVERSITIES ORIGINALLY PROVIDED FOR UNDER ORDINANCE NO. 5696, S-2015 SUBJECT TO ALL ACCOUNTING, AUDITING & LEGAL RULES AND REGULATIONS ON THE MATTER | C127: AT Republic of the Philippines SANGGUNIANG PANLUNGSOD Pasay City Ordinance No. 6064, S-2019 IO R DB IT N A N €C EE INDIVIDUALS AVAILING OF SCHOLARSHIP GRANTS AND FINANCIAL ASSISTANCE TO HIGH SCHOOL AND COLLEGE STUDENTS IN PUBLIC AND PRIVATE COLLEGES AND UNIVERSITIES ORIGINALLY PROVIDED FOR UNDER ORDINANCE NO. 5696, S-2015 SUBJECT TO ALL ACCOUNTING, AUDITING & LEGAL RULES AND REGULATIONS ON THE MATTER Sponsored by Vice Mayor NOEL L. DEL ROSARIO Co-sponsored by City Councilors MARK ANTHONY A. CALIXTO, ALLAN _T. PANALIGAN, MARY GRACE B. SANTOS, DONNABEL M. VENDIVEL, : ANTONIA C. CUNETA, ARNEL REGINO T. ARCEO, ABRAHAM ALBERT Q. ALVINA, JOSE C. ISIDRO, JR.. MARLON A. PESEBRE, EDITHA Y. MANGUERRA, RICARDO E. SANTOS, AILEEN C. PADUA, JULIE G. GONZALES and JOSE MIGUEL A. MANEZ ine US Be it enacted by the Sangguniang Panlungsod in session duly assembled: Section 1. Basic Qualifications/Criteria For Financial Assistance. — The basic qualifications or criteria for financial assistance for those individuals availing of scholarship grants and financial assistance to high school and college students in public and private colleges and universities originally provided for under Ordinance No. 5696, S-2015 subject to all accounting, auditing & legal rules and regulations on the matter are as follows, to wit: a. Bona fide resident of Pasay City for at least three (3) years immediately preceding the application; b. Must be a registered voter of the City if 18 years or older upon application; if minor at least one of the parents or guardian is aregistered voter of the city; c. Certificate of Eligibility or indigency coming from PSWD; d. For High School Students: Applicant must have at least 80% General Weighted Average (GWA) with NO failing final grades; e. For College Students: Applicants must have a general weighted average of at least 80% or its equivalent for the semester/trimester immediately prior to his/her application, at least 12 academic units load for non- ee students; and dropped, failing or filete grades must have a supporting documents r) istification; AN ORDINANCE PROVIDING FOR THE BASIC } QUALIFICATIONS/CRITERIA FOR FINANCIAL ASSISTANCE FOR THOSE : \ , Page 2 of Ordinance No. 6064, S-2019 Lge f. All applicants must be determined to finish the course within the given period corresponding to the type of scholarship granted; g. Must not be students of the City University of Pasay whose students are already covered b a different scholarship grants and/or students of DepEd public high schools; and h. Committed to love and serve Pasay City Section 2. Effectivity. — This ordinance shall take effect upon passage by the Sangguniang Panlungsod, approval by the City Mayor and posting in three (3) conspicuous places in the City of Pasay. ORDAINED in the City of Pasay, Metro Manila, Philippines, this 11" day of November, in the Year of Our Lord, Two Thousand Nineteen. CERTIFIED APPROVED BY THE SANGGUNIANG PANLUNGSOD District- I jPoerreerrne® SEA OO RSTRNT Hon. MARK ANTHONY A. CALIXTO City Councilor ; i fis Ris Hon. MARY GRACE B. SANTOS City Councilor Hon. MA. ANTONIA C. CUNETA City Councilor t Hon. ABRAHAM ALBERT Q. ALVINA City Councilor eg Sg. = Hon. MARLON A. PESEBRE City Councilor Yy.__ Hon. RIC O E. SANTOS City Councilor Dey — NAN T. PANALIGAN Councilor Hon. DONNABEL|;M. VENDIVEL City Councilor Hon. ARNEL REGINO T. ARCEO City ee PS te nll es Coe J Hon. JOSE C. ISIDRO, JR. City Councilor Hon. EDITHA Y. GUE City Councilor (joe Hon. AILEEN C. PADUA City Councilor ‘ ‘ “ - * Page 3 of Ordinance No. 6064, S-2019 Hon. ak &. NZALES President Liga ng mga Barangay Pasay City Chapter Attested by: Ex-Officio Members Pont Hon. JOSE MIGUEL A. MANEZ President Sangguniang Kabataan Federation } S) Pasay City Chapter _J Finis Certified True Copy: RTO B. YAM Hon. NOEL L. DEL ROSARIO City Vice-Mayor & Presiding Officer Approved: fo HO LDA ae ee O City Mayor Cry Secretary N { | D127: Pasay | E127: 0.47402597 | F127: 56.7826
A128: 6060 | B128: AN ORDINANCE AMENDING SECTIONS 4 AND 5 OF ORDINANCE NO. 4367, SERIES OF 2008 OTHERWISE KNOWN AS "AN ORDINANCE PRESCRIBING THE SANITATION CODE OF PASAY CITY" TO REQUIRE ALL KINDS OF WORKERS AND EMPLOYEES, INCLUDING FOREIGNERS DESIRING TO WORK IN ANY INDUSTRY, BUSINESS OR ESTABLISHMENT OPERATING OR DOING BUSINESS WITHIN THE TERRITORIAL JURISDICTION OF THE CITY OF PASAY TO SECURE HEALTH PERMIT FROM THE CITY HEALTH OFFICE PRIOR TO EMPLOYMENT SUBJECT TO COMPLIANCE WITH PERTINENT LAWS, RULES AND REGULATIONS ON THE MATTER. | C128: Republic of the Philippines Lungsod Ng Pasay, Kalakhang Maynila Tanggapan ng Sangguniang Panlungsod AN ORDINANCE AMENDING SECTIONS 4 AND 5 OF ORDINANCE NO. 4367, SERIES OF 2008, OTHERWISE KNOWN AS “AN ORDINANCE PRESCRIBING THE SANITATION CODE OF PASAY CITY” TO REQUIRE ALL KINDS OF WORKERS AND EMPLOYEES, INCLUDING FOREIGNERS, DESIRING TO WORK IN ANY INDUSTRY, BUSINESS OR ESTABLISHMENT, OPERATING OR DOING BUSINESS WITHIN THE TERRITORIAL JURISDICTION OF THE CITY OF PASAY TO SECURE HEALTH PERMIT FROM THE CITY Nv HEALTH OFFICE PRIOR TO EMPLOYMENT SUBJECT TO COMPLIANCE WITH PERTINENT LAWS, RULES AND REGULATIONS ON THE MATTER Ordinance No®"®&eries of 2019 ) Introduced by: Vice Mayor Noel L. Del Rosario Sponsored by: Councilors Mark Anthony A. Calixto, Mary Grace B. Santos, Ma. Antonia C. Cuneta, Abraham Albert Q. Alvina, Marlon A. Pesebre, Ricardo E. Santos, | | d, Allan T. Panaligan, Donnabel M. Vendivel, Arnel Regino T. Arceo, Jose C. Isidro, Jr., ) Editha Y. Manguerra, Aileen C. Padua, Julie G. Gonzales and Jose Miguel A. Maftez (\ WHEREAS, a proposed ordinance is presented before the Sangguniang Panlungsod for its consideration entitled “An Ordinance Mandating All Kinds of Workers and Employees, Including Foreigners, Desiring to Work Within the Territorial Jurisdiction of the City of Pasay to Annually Secure a Working Health Permit from the City Health office Prior to Employment Subject to All Applicable Laws, Rules and Regulations on the Matter’; WHEREAS, the subject matter was set for hearing on October 7, 2019 wherein representatives from the Office of the City Health officer and Public Employment Service Office (PESO) were invited as resource speakers. With the influx of foreign workers to the business centers within the territorial jurisdiction of Pasay City especially within the SM Mall of Asia (MOA) Complex due to the unstoppable progress and development in the City, many businesses also hire foreign workers such as online gaming operations and the flourishing tourist industry in the City. However, while this is a sign of development, the increasing numbers of foreign workers in the City also pose different consequences and threats such as increase in crime rates and proliferation of health related issues; WHEREAS, our existing ordinances related on the matter do not cover foreign workers. As such, foreign workers secure their health permits from the Department of Labor and Employment (DOLE) with the exclusion of the City Government. It appeared that the existing ordinances of the city on the issuance of work and permit and health clearance are the following: 1. Ordinance No. 1331, Series 1998 - “An Ordinance Amending Ordinance Providing for the Mandatory Attendance of All Applicants for Mayor’s Work Permit/License or Occupational Health Permits/Certificates to an AIDS/STD Awareness Seminar and Providing Penalties for Violations Thereof” In so Far as Section III-Fees is Concerned, Increasing the Fee of Ten Pesos (P10.00) to Fifty Pesos (P50.00) Per Participant as Provided Therein’; MO. fe 2. Ordinance No. 1612, Series 1999 - “An Ordinance Regulating the Issuance of Work Permit and Health Clearance for Private Employment;” and washer No. 4367, Series of 2008 - “An Ordinance Prescribing the sanitation Codehie asay City”’; “Y Page 2 of 4 ete No. 606 Q ies 2019 “AN ORDINANCE AMENDING a | 5S OF ORDINANCE NO. 4367, SERIES OF 2008, OTHERWISE KNOWN AS “AN ORDINANCE PRESCRIBING THE SANITATION CODE OF PASAY CITY” TO REQUIRE ALL KINDS OF WORKERS AND EMPLOYEES, INCLUDING FOREIGNERS, DESIRING TO WORK IN ANY INDUSTRY, BUSINESS OR ESTABLISHMENT, OPERATING OR DOING BUSINESS WITHIN THE TERRITORIAL JURISDICTION OF THE CITY OF PASAY TO SECURE HEALTH PERMIT FROM THE CITY HEALTH OFFICE PRIOR TO EMPLOYMENT SUBJECT TO COMPLIANCE WITH PERTINENT LAWS, RULES AND REGULATIONS ON THE MATTER” Xnn mannan nnn nanan nnn ~--X WHEREAS, under the Sanitation Code of Pasay City, health certificate are only required to be secured by employees employed in specific industries such as those which are related to food and water, public and private market, and those employed in dancing halls, night clubs, massage clinics, sauna baths, fitness gym, spa and music lounge operating and doing business within the territorial jurisdiction of the City of Pasay; WHEREAS, during the Joint Committee Hearing, it was agreed upon by the members of the Sangguniang Panlungsod that instead of enacting a new City Ordinance covering all workers and employees employed in any other industry aside from those enumerated and mentioned under the Sanitation Code of Pasay City to require them to secure Health Permit to be issued by the City Health Office without distinction, including foreign workers, it would be more prudent to just amend the existing ordinances of the City pertaining to this matter; NOW THEREFORE, BE IT ENACTED, AS IT IS HEREBY ENACTED, BY THE SANGGUNIANG PANLUNGSOD OF PASAY, IN SESSION ASSEMBLED, BY VIRTUE OF THE POWERS VESTED IN IT BY LAW, THAT: Section 1. Chapter II, Section 4 of Ordinance No. 4367, Series of 2008 is hereby amended to be read as follows: “Chapter II HEALTH CERTIFICATE Section 4. All kinds of workers and employees, without distinction, including foreigners, employed in all industries, businesses and establishments operating and doing business within the territorial jurisdiction of Pasay City are required to secure a health certificate at the City Health Office and work permit from the City Government of Pasay.” Section 5. Food Handler’s Training are required for applicants of Health Certificate working in food establishments only. Applicants for a Health Certificate as required in this Code shall undergo the following training and tests and submit the original certificate of completion and certification of the results of the tests: For White Card Applicants: XXX For Pink Card Applicants: XX X For other Applicants (other industries): Routine Urinalysis; be Chest X-Ray (valid for One (1) Year); 3. Drug Test (Pursuant to Ordinance No. 1609, Series of 1999); and 4, Undergo AIDS/STD Awareness Seminar (Pursuant to Ordinance No. 1331, Series of 1998.” Section 2. Information Dissemination. — Being the head implementing agency of the Sanitation Code of the City, the Pasay City Health Office, in coordination with the Public Information Office, Liga ng mga Barangay, Barangay Bureau, the 201 barangays of Pasay City, BPLO an@athether agencies which could help in the dissemination of information with aaa 2 a ys erp h/ G7 Gi _ oy _ Page 3 of 4 yOrdinance No. , Series 2019 *AN ORDINANCE AMENDING SECT & AND 5S OF ORDINANCE NO. 4367, SERIES OF 2008, OTHERWISE KNOWN AS “AN ORDINANCE PRESCRIBING THE SANITATION CODE OF PASAY CITY” TO REQUIRE ALL KINDS OF WORKERS AND EMPLOYEES, INCLUDING FOREIGNERS, DESIRING TO WORK IN ANY INDUSTRY, BUSINESS OR ESTABLISHMENT, OPERATING OR DOING BUSINESS WITHIN THE TERRITORIAL JURISDICTION OF THE CITY OF PASAY TO SECURE HEALTH PERMIT FROM THE CITY HEALTH OFFICE PRIOR TO EMPLOYMENT SUBJECT TO COMPLIANCE WITH PERTINENT LAWS, RULES AND REGULATIONS ON THE MATTER” Mannnnnnnnnnnnnn nnn nnnnnnnnnnnnnnnnnnnnnnennnnnnnnnnnmananane x regard to the new policy of the City, is hereby directed to formulate strategies and conduct regular trainings and seminars to employer and employees alike relative to the requirements needed and the procedure in securing health certificate. Section 3. Repealing Clause. — All provisions of ordinances contrary to or inconsistent with this Ordinance are hereby repealed or modified accordingly. Section 4. Effectivity Clause. —- This Ordinance shall take effect in accordance with the provisions of the Local Government Code of 1991. ENACTED, thie FR of ect’. 2019, Pasay City, Philippines CERTIFIED APPROVED BY THE SANGGUNIAN UNGSOD: District-] istrict-I] Hon. MARK ANTHONY A. CALIXTO PANALIGAN City Councilo UM hs Kf AN Hon. | e- GRACE B. SANTOS Hon. DONNABE/M. VENDIVEL City Counpiloy a { City Councilor Hon. MA.ANFONIA C. CUNETA Hon. ARNEL O T. ARCEO City Councilor, A City Councilor [pbite Hon. ABRAHAM ALBERT Q. ALVINA OSE C, ISIDR City Councilor City Counci eee ao Hon. MARLON A. PESEBRE Hon. EDIT - MANGUDERRA City Coungilor City 4 Hon. RICARDO E. SANTOS Hon. AILEEN C. PADUA City Councilor City Councilor Ex-Officio Members ihe!” Hon’ JULIE G..GONZALES Hon. JOSE MIGUEL A. MANEZ President President Liga ng mga Barangay SK Federation Pasay Chapter Pasay Chapter Certified, True Copy: % Pageaota & ' »Ordinanco No. ___, Series 2019 $ 4 t “AN ORDINANCE AMENDING secu Po S OF ORDINANCE NO. 4367, SERIES OF 2008, OTHERWISE KNOWN AS “AN ORDINANCE PRESCRIBING THE SANITATION CODE OP PASAY CITY” TO REQUIRE ALL KINDS OF WORKERS AND EMPLOYEES, INCLUDING FORKIGNERS, DESIRING TO WORKIN ANY INDUSTRY, BUSINESS OR ESTABLISHMENT, OPERATING OR DOING OUSINESS WITHIN THE TERRITORIAL JURISDICTION OF THE CITY OF PASAY TO SECURE HEALTH PERMIT FROM TUE CITY HEALTH OFFICE PRIOR TO EMPLOYMENT SUBJECT TO COMPLIANCE WITH PERTINENT LAWS, RULES AND REGULATIONS ON THE MATTER* mr rrr ee rere mentee mmm temas manenns meme asin eemenanen om mmmyam an Wf Attested by: Hon. NOEL L. DEL ROSARIO City Vice Mayor & Presiding Officer c Approved by: Hon. IMELDA G. CALIXTO-RUBIANO City Mayor DEEMED APPROVED AFTER THE LAPSED OF TEN hited R SEC, SARA 00 | D128: Pasay | E128: 0.47402597 | F128: 56.7826
A129: 6056 | B129: AN ORDINANCE AUTHORIZING THE OFFICERS AND MEMBERS OF THE SANGGUNIANG PANLUNGSOD TO UNDERTAKE PLANS, PROJECTS, PROGRAMS AND ACTIVITIES FOR THE IMPLEMENTATION OF SECTION 16 OF THE LOCAL GOVERNMENT CODE OF 1991 PERTAINING TO GENERAL WELFARE TO ASSIST THE LOCAL CHIEF EXECUTIVE IN ATTAINING HER PROGRAMS OF GOVERNMENT WITH THE ACRONYM H.E.L.P. WHICH STANDS, AMONG OTHERS, FOR HEALTH, HOUSING, EDUCATION, ECONOMIC GROWTH, ENVIRONMENT, LIVELIHOOD, LIFESTYLE, PEACE & ORDER, PALENGKE, PAMILYA AND PUBLIC GOVERNANCE | C129: ( . Republic of the Philippines SANGGUNIANG PANLUNGSOD Pasay City Ordinance No. ©€56 , S-2019 + GO RK DB IT N A N C€C EE AN ORDINANCE AUTHORIZING THE OFFICERS AND MEMBERS OF THE SANGGUNIANG PANLUNGSOD TO UNDERTAKE PLANS, PROJECTS, PROGRAMS AND ACTIVITIES FOR THE IMPLEMENTATION OF SECTION 16 OF THE LOCAL GOVERNMENT CODE OF 1991 PERTAINING TO GENERAL WELFARE TO ASSIST THE LOCAL CHIEF EXECUTIVE IN ATTAINING HER PROGRAMS OF GOVERNMENT WITH THE ACRONYM H.E.L.P. WHICH STANDS, AMONG OTHERS, FOR HEALTH, HOUSING, EDUCATION, ECONOMIC GROWTH, ENVIRONMENT, LIVELIHOOD, LIFESTYLE, PEACE & ORDER, PALENGKE, PAMILYA AND PUBLIC GOVERNANCE an Sponsored by Vice Mayor NOEL L. DEL ROSARIO Co-sponsored by City Councilors MARK ANTHONY A. CALIXTO, ALLAN T. PANALIGAN, MARY GRACE B. SANTOS, DONNABEL M. VENDIVEL, MA ANTONIA C. CUNETA, ARNEL REGINO T. ARCEO, ABRAHAM ALBERT oN ALVINA, JOSE C. ISIDRO, JR., MARLON A. PESEBRE, EDITHA Y. MANGUERRA aN RICARDO E. SANTOS, AILEEN C. PADUA, JULIE G. GONZALES and JOSE |P-< ~ MIGUEL A. MANEZ | WHEREAS, the Black’s Law Dictionary has defined the words General Welfare x as the general term used to describe the government’s concern for the health peace, morals and safety of its citizens. NOW THEREFORE, BE IT ENACTED, by the Sangguniang Panlungsod of Pasay in session duly assembled: Section 1. General Welfare. — The officers and members of the Sangguniang Panlungsod are hereby authorized to undertake plans, projects, programs and activities for the implementation of Section 16 of the Local Government Code of 1991 pertaining to General Welfare to assist the Local Chief Executive in attaining her programs of government with the acronym H.E.L.P. which stands, among others, for Health, Housing, Education, Economic Growth, Environment, Livelihood, Lifestyle, Peace & Order, Palengke, Pamilya and Public Governance. Sangguniang Panlungsod, approval by the City Mayor and posting in three (3) conspicuous places in the City of Pasay. Section 2. Effectivity. — This Ordinance shall take effect upon passage by the I ORDAINED, this 2ist day of October in the Year of Our Lord Two Thousand Nineteen. 4 Uh L u R A —_ . » is ’ 60 ? °¢? of Ordinance No. 56 _§-2019 CERTIFIED APPROVED BY THE SANGGUNIANG PANLUNGSOD District - I Hon. MARK ANTHONY A. CALIXTO City Councilor Hon. MARY GRACE B. SANTOS Ci cilor City Councilor Hon. ABRAHAM ALBERT Q. ALVINA City Councilor So ae Hon. MARLON A. PESEBRE City Councilor Hon. RICARDO E. SANTOS City Councilor Ex-Officio Members ay 2 94 GONZALES President Liga ng mga Barangay Pasay City Chapter Attested by: Hon. NOEL L. DEL ROSARIO City Vice-Mayor & Presiding Officer Approved by: bon ee re CALIXTO-RUBIAN O \ h MZ Hon. AE Ni iN T. PANALIGAN a\ GINO T. ARCEO City C ilor oh C. ISIDRO, JR. City Councilor Hon. EDITHA Y. MANGUE City Councilor Hon. AILEEN C. PADUA City Councilor ae Hon. JOSE MIGUEL A. MANEZ President Sangguniang Kabataan Federation Pasay City Chapter | D129: Pasay | E129: 0.47402597 | F129: 56.7826
A130: 6053 | B130: AN ORDINANCE AMENDING SECTION 2 OF ORDINANCE NO. 4413, S-2009 TO INCLUDE ALL SCREENINGS OF FRIDAYS IN THE FREE ADMISSION OF THE DULY REGISTERED SENIOR CITIZENS OF PASAY IN ALL MOVIE HOUSES, THEATERS AND CINEMAS WITHIN THE JURISDICTION OF PASAY CITY. | C130: fonp Republic of the Philippines SANGGUNIANG PANLUNGSOD Pasay City, Metro Manila ee Ordinance No. ©8953 —_, S-2019 ORDINANCE AN ORDINANCE AMENDING SECTION 2 OF ORDINANCE NO. 4413, S-2009 TO INCLUDE ALL SCREENINGS OF FRIDAYS IN THE FREE ADMISSION OF THE DULY REGISTERED SENIOR CITIZENS OF PASAY IN ALL MOVIE HOUSES, THEATRES AND CINEMAS WITHIN THE JURISDICTION OF PASAY CITY. Introduced by Vice Mayor Noel L. Del Rosario Sponsored by Honorable Councilor Marlon A. Pesebre Co-Sponsored by Honorable Councilors Mark Anthony A. Calixto, Mary Grace B. Santos, Ma. Antonia C. Cuneta, Abraham Albert Q. Alvina, Ricardo E. Santos, Allan T. Panaligan, Donnabel M. Vendivel, Arnel Regino T. Arceo, Jose C. Isidro, Jr., Editha Y. Manguerra, Aileen C. Padua, Julie G. Gonzales and Jose Miguel A. Mafiez WHEREAS, the pertinent provision of Section 2 of Ordinance No. 3943, S-2007 are as NG follows: “Section 2. ADDITIONAL PRIVILEGE GRANTED BY THE CITY. Pursuant to this policy, all duly registered senior citizens of Pasay City are granted the privilege of free admission in all regular movie houses, theatres and cinemas located in Pasay City in all screening of movies on Mondays and Tuesdays and first screening of movies on Thursdays of the week subject to the conditions prescribed in Section 3 thereof.” WHEREAS, the above mentioned provision was further amended by City Ordinance No. 4413, S-2009 wherein free admission for senior citizens during Thursdays was made for the whole day, the pertinent provision thereof 1s quoted below, to wit: “Section 1. AMENDMENT - Section 2 of Ordinance No. 3943, Series of 2007 is hereby amended, to read as follows: ‘Section 2. ADDITIONAL PRIVILEGE GRANTED BY THE . CITY. Pursuant to this policy, all duly registered senior citizens of Pasay City are granted the privilege of free admission in all regular movie houses, theatres and cinemas located in Pasay City in all ; screening of movies on Mondays and Tuesdays and Thursdays of the week subject to the conditions prescribed in Section 3 thereof.” (Emphasis supplied) registered senior citizen of Pasay City, to include all screenings of Friday for them to enjoy the movies being shown in thega4staadi shments; At WHEREAS, there is a E to amend the privilege being granted by the City to the duly ee 4 : | AA vn Page 2of 3 Ordinance No. 6653 , Series of 2019. AN ORDINANCE AMENDING SECTION 2 OF ORDINANCE NO. 4413, S-2009 TO INCLUDE ALL SCREENINGS OF FRIDAYS IN THE FREE ADMISSION OF THE DULY REGISTERED SENIOR CITIZENS OF PASAY IN ALL MOVIE HOUSES, THEATRES AND CINEMAS WITHIN THE JURISDICTION OF PASAY Tt Naw wer we cnn a en enn ee en nnn ee cee ween ees NOW THEREFORE, BE IT ENACTED, AS IT IS HEREBY ENACTED, BY THE SANGGUNIANG PANLUNGSOD OF PASAY, IN SESSION ASSEMBLED, BY THE VIRTUE OF THE POWERS VESTED IN IT BY LAW, THAT: Section 1. AMENDMENT - Section 2 of Ordinance No. 4413, S-2009 is hereby amended as follows: “Section 2. ADDITIONAL PRIVILEGE GRANTED BY THE CITY. Pursuant to this policy, all duly registered senior citizens of Pasay City are granted the privilege of free admission in all regular movie houses, theatres and cinemas located in Pasay City in all screening of movies on Mondays, Tuesdays, Thursdays and Fridays of the week subject to the conditions prescribed in Section 3 thereof.” Section 2. EFFECTIVITY — This ordinance shall take effect upon passage of the Sangguniang Panlungsod, approval of the City Mayor and one (1) day after posting in three (3) conspicuous places in the City of Pasay. ENACTED in the City of Pasay, Metro Manila, Philippines, this 7th day of Octeber , 2019. CERTIFIED AND APPROVED BY THE SANGG District - I Hon. MARK ANTHONY A. CALIXTO Hon. AMY City Councilor 1 Acting Presiding Officer Hon. MARY RACE B. SANTOS Hon. MA. Hon _— O T. ARCEO — Councilor on FT 34 ! , | Hon. ABRAHAM ALBERT Q. ALVINA OSE C. ISIDR City Councilor City Councilor tg Hon. MARLON A. PESEBRE Hon. EDITHA Y: MANGUERRA City Councilor City Councilor Hon. RICARDO E. SANTOS Hon. AILEEN C. PADUA City Councilor City Councilor ' “a * \ 4 Page 30f3 — Ordinance No. 6 oS BE) , Series of 2019. AN ORDINANCE AMENDING SECTION 2 OF ORDINANCE NO. 4413, S-2009 TO INCLUDE ALL SCREENINGS OF FRIDAYS IN THE FREE ADMISSION OF THE DULY REGISTERED SENIOR CITIZENS OF PASAY IN ALL MOVIE HOUSES, THEATRES AND CINEMAS WITHIN THE JURISDICTION OF PASAY CITY. No woe ee ee ee ee ee - - - - - - - - + ++ x ) Ex-Officio Members J sa ic G. GONZALES Hon. JOSE MIGUEL A. MANEZ President President Liga Ng Mga Barangay SK Federation Pasay City Chapter Pasay City Chapter Certified True Co Attested by: i ee eee 4 FT AAs Ze Ope Lin way dt ~~ Hon. NOEL L. DEL ROSARIO City Vice-Mayor & Presiding Officer Approved by: Pe Hon. IMELDA G. CALIXTO-RUBIAWO City Mayor | D130: Pasay | E130: 0.47402597 | F130: 56.7826
A131: 6052 | B131: AN ORDINANCE PROVIDING FOR THE CLUSTERING OF CHILD-FRIENDLY FACILITIES ESTABLISHED IN ALL BARANGAYS IN THE CITY OF PASAY AND MANDATING THE SHARING OF THESE FACILITIES TO ADJACENT AND NEARBY BARANGAYS | C131: Republic of the Philippines OFFICE OF THE SANGGUNIANG PANLUNGSOD Pasay City, Metro Manila AN ORDINANCE PROVIDING FOR THE CLUSTERING OF CHILD-FRIENDLY FACILITIES ESTABLISHED IN ALL BARANGAYS IN THE CITY OF PASAY AND MANDATING THE SHARING OF THESE FACILITIES TO ADJACENT AND NEARBY BARANGAYS ORDINANCENO. 6052 ,SERIES OF 2019 Introduced by: Vice Mayor Noel L. Del Rosario Sponsored by: Councilors Mark Anthony A. Calixto, Mary Grace B. Santos, Ma. Antonia C. Cuneta, Abraham Albert Q. Alvina, Marlon A. Pesebre, Ricardo E. Santos, Allan T. Panaligan, Donnabel M. Vendivel, Arnel Regino T. Arceo, Jose C. Isidro, Jr., > Editha Y. Manguerra, Aileen C. Padua, Julie G. Gonzales and Jose Miguel A. Maiiez | WHEREAS, Section 2(4), Article XIV of the 1987 Philippine Constitution provides that “The State shall encourage non-formal, informal, and indigenous learning systems, as well as self-learning, independent, and out of school study programs particularly those that respond to the community needs”; WHEREAS, Section 2 of Republic Act No. 8980, also known as the “Early Childhood Care and Development (ECCD) Act” declares that it 1s the policy of the State to promote th rights of children to survival, development, and special protection; WHEREAS, Republic Act No. 6972 entitled “Barangay-Level Total Development and protection of Children Act”, declares that Filipino children up to Six (6) years of age deserve the best care and attention at the family and community levels. Towards this end, there is hereby established a day care center in every Barangay with a total development protection of children as provided for by the said Act instituted in every barangay day care center; WHEREAS, City Ordinance No. 5809, Series of 2017, otherwise known as the I Updated Local Code for Children declares that the City of Pasay recognizes the vital role of the youth in nation-building and shall promote and protect their physical, moral, spiritual, intellectual, and social well-being and that it shall inculcate in the youth patriotism and nationalism, and encourage their involvement in public and civic affairs; WG WHEREAS, the City of Pasay has a very limited space and 1s divided into 201 barangays which makes it difficult to establish child-friendly facilities such as play grounds, recreational areas, libraries, reading centers and the like in each barangay; Page 2: Ordinance No. 605 2 , Series of 2039. “AN’ ORDINANCE PROVIDING FOR’ THE CLUSTERING OF CHILD-FRIENDLY FACILITIES ES@ABLISHED IN ALL BARANGAYS IN THE CITY OF PASAY AND MANDATING THE SHARING OF THESE FACILITIES TO ADJACENT AND NEARBY BARANGAYS” Xr NOW THEREFORE, BE IT ORDAINED, AS IT IS HEREBY ORDAINED, by the Sangguniang Panlungsod of Pasay, in session assembled, PROVIDING FOR THE CLUSTERING OF CHILD-FRIENDLY FACILITIES ESTABLISHED IN ALL BARANGAYS IN THE CITY OF PASAY AND MANDATING THE SHARING OF THESE FACILITIES TO ADJACENT AND NEARBY BARANGAYS. ENACTED in the City of Pasay, Metro Manila, Philippines this @th day of Octeber in the Year of Our Lord, Two Thousand Nineteen. District-I eta tay Hon. MARK ANTHONY A. CALIXTO City Councilor (On Leave) Hon. ABRAHAM ALBERT Q. ALVINA City Councilor Hon. MARLON A. PESEBRE City Councilo ) A Hon. RIC O E. SANTOS City Councilor ap Ex-Officio Members Hon. ae! G. NZALES President Liga ng mga Barangay Pasay Chapter Certified True Copy; Hon. DONNABEL/M. VENDIVEL City Councilor Hon. ARNEL INO T. ARCEO City Councilor Hon. AILEEN GC. PADUA City Councilor Hon. JOSE MIGUEL A. MANEZ President SK Federation Pasay Chapter Page 2: Ordinance No. 605 a. Series of 2089. “AN: ORDINANCE PROVIDING FOR’ THE CLUSTERING OF CHILD-FRIENDLY FACILITIES ESTABLISHED IN ALL BARANGAYS IN THE CITY OF PASAY AND MANDATING THE SHARING OF THESE FACILITIES TO ADJACENT AND NEARBY BARANGAYS” N--—--—--+-- ~~ ----—-—--—-—--—-—--- —-- —------ Attested by: (On Leave) Hon. NOEL L. DEL ROSARIO City Vice Mayor & Presiding Officer Approved by; ZO (— Hon. IMELDA G. CALIXTO-RUBIANO City Mayor \ | D131: Pasay | E131: 0.47402597 | F131: 56.7826
A132: 6051 | B132: AN ORDINANCE ADOPTING THE "CHILDREN'S SAFETY ON MOTORCYCLES ACT OF 2015" AND THEREBY PROHIBITING THE RIDING OR TRANSPORTING OF SMALL CHILDREN ON MOTORCYCLES AND TRICYCLES IN FRONT OR AT THE BACK OF THE DRIVER'S SEAT ALONG HIGHWAYS AND PUBLIC ROADS WITHIN THE CITY OF PASAY | C132: Republic of the Philippines SANGGUNIANG PANLUNGSOD Pasay City, Metro Manila ‘. Ordinance No. 6051 _§-2019 Ny GO KR DINAN CE AN ORDINANCE ADOPTING THE “CHILDREN’S SAFETY ON MOTORCYCLES ACT OF 2015” AND THEREBY PROHIBITING THE RIDING OR TRANSPORTING OF SMALL CHILDREN ON MOTORCYCLES AND TRICYCLES IN FRONT OR AT THE BACK OF THE DRIVER’S SEAT ALONG HIGHWAYS AND PUBLIC ROADS WITHIN THE CITY OF PASAY Introduced by Vice Mayor Noel L. Del Rosario Sponsored by Councilors Mark Anthony A. Calixto, Mary Grace B. Santos, Ma. Antonia C. Cuneta, Abraham Albert Q. Alvina, Marlon A. Pesebre, Ricardo E. Santos, Allan T. Panaligan, Donnabel M. Vendivel, Arnel Regino T. Arceo, Jose C. Isidro, Jr., Editha Y. Manguerra, Aileen C. Padua, Julie G. Gonzales and Jose Miguel A. Majfiez WHEREAS, Section 1, Article XIII of the 1987 Philippine Constitution provides that “Congress shall give highest priority to the enactment of measures that protect and enhance the right of all the people to human dignity, reduce social, economic, and political inequalities, and remove cultural inequities by equitably diffusing wealth and political power for the commo good” and “to this end, the State shal! regulate the acquisition, ownership, use, and disposition o property and its increments.” SS WHEREAS, Republic Act No. 10666, otherwise known as “An Act Providing for the Safety of Children Aboard Motorcycles” declared that it is “the policy of the State to defend the right of children to assistance, including proper care and nutrition, and special protection from all forms of neglect, abuse, cruelty, exploitation, and other conditions prejudicial to their development. Towards this end, the State shall pursue a more proactive and preventive approach to secure the safety of passengers, especially children, by regulating the operation of motorcycles along roads and highways;” WHEREAS, the Republic Act No. 7160, better known as the Local Government Code of 1991, Section 16 thereof states that: Section 16. General Welfare. - Every local government unit shall exercise the powers expressly granted, those necessarily implied therefrom, as well as powers necessary, appropriate, or incidental for its efficient and effective governance, and those which are essential to the promotion of the general welfare. Within their respective territorial jurisdictions, local government units shall ensure and support, among other things, the preservation and enrichment of culture, promote health and safety, enhance the right of the people to a balanced ecology, encourage and support the development of appropriate and self-reliant scientific and technological capabilities, improve public morals, enhance economic prosperity and social justice, promote full employment among their residents, maintain peace and order, and preserve the comfort and convenience of their inhabitants; ee | 4 ‘ Page 2 of 4 | ; ae 6051 ee No. Series of 2019. AN ORDINANCE ADOPTING THE “CHILDREN’S SAFETY ON MOTORCYCLES ACT OF 2015” AND THEREBY PROHIBITING ~ THE RIDING OR TRANSPORTING OF SMALL CHILDREN ON MOTORCYCLES AND TRICYCLES IN FRONT OR AT THE BACK OF THE DRIVER’S SEAT ALONG HIGHWAYS AND PUBLIC ROADS WITHIN THE CITY OF PASAY. Si nahh a i i ab et“ eb a aan gas “ata Yad a a 5 : LOE WHEREAS, the City Government of Pasay recognizes the fact that motorcycles and tricycles are widely utilized as school services in transporting children to and from their respective schools. As such, it is necessary to intensify the policies of the City in ensuring their safety while they are in transit; WHEREAS, it is a known fact that kids are more excitable and have the tendency to move more than an adult passenger. They may even play games by sticking their hands out in the wind while riding a motorcycle. Moreover, they generally want to talk and move more than an adult passenger; WHEREAS, likewise, the steady rumble of the motor can have a tendency to lul passengers to sleep. With adults, this usually does not present much of a problem since it would d be harder for them to fall off. But with children, it is completely different situation. Because of their size, there is generally more room for them between the rider and the sissy rider bar and when they fall asleep, there is a great chance for them to flop over to one side or another. When this happens, there is an increased chance for children to fall off the motorcycle; NOW THEREFORE, BE IT ENACTED, AS IT IS HEREBY ENACTED, B THE SANGGUNIANG PANLUNGSOD OF PASAY, IN SESSION ASSEMBLED, BY “ THE VIRTUE OF THE POWERS VESTED IN IT BY LAW, THAT: SECTION 1. SHORT TITLE. — This Ordinance shall be known as “Pasay City Motorcycl and Tricycle Safety Ordinance for Children.” SECTION 2. DECLARATION OF POLICY. — The City of Pasay recognizes its role to maintain at all times the safety and protection of children. SECTION 3. DEFINITIONS. - For the purpose of this Ordinance, the following terms shall mean: (a) Motorcycle refers to any two (2)-wheeled motor vehicle having one (1) or two (2) riding saddles; (b) Tricycle refers to any vehicle having three wheels, two at the back and one at the front; units as roads for public use such as, but not limited to, national highways, provincial roads, city, municipal and barangay streets; (c) Foot peg refers to a flat form attached to the motorcycles on which to stand or brace the feet; and (b) Public roads refer to roads designed by the national government or local government . (d) Rider refers to the driver of a motorcycle. SECTION 4. PROHIBITION. — It shall be unlawful for any person to drive a two (2)-wheeled motorcycle with a child on board or a tricycle operating anywhere within the City from conveying small children in front or at the back of the driver’s seat on any of the public roads in the City of Pasay where there is heavy volume of vehicles, Page 3 of 4 | ya ~Irdinance No. 6051 Series of 2019. AN ORDINANCE ADOPTING THE “CHILDREN’S SAFETY ON MOTORCYCLES ACT OF 2015” AND THEREBY PROHIBITING THE RIDING OR TRANSPORTING OF SMALL CHILDREN ON MOTORCYCLES AND TRICYCLES IN FRONT OR AT THE BACK OF THE DRIVER’S SEAT ALONG HIGHWAYS AND PUBLIC ROADS WITHIN THE CITY OF PASAY. No wo ww a ww en on ww oe one ee ee ee eee Xx (a) The child passenger can comfortably reach his/her feet on the standard foot peg of the motorcycle; (b) The child’s arms can reach around and grasp the waist of the motorcycle rider; and (c) The child is wearing a standard protective helmet referred to under Republic Act No. 10054, otherwise known the "Motorcycle Helmet Act of 2009." SECTION 5. EXCEPTION. — Notwithstanding the prohibition provided in the preceding section, this Ordinance shall not apply to cases where the child to be transported requires immediate medical attention. SECTION 6. PENALTIES. Any violations of this Ordinance shall be punished as follows: a. The first time offender shall be fined with an amount of P2,000.00. b. The second time offender, the fine shall be P3,000.00. c. For third and succeeding offenders, the fine shall be P5,000.00 or imprisonment for a maximum of six months, or both, at the discretion of the court. SECTION 7. PASAY CITY TRAFFIC AND PARKING MANAGEMENT OFFICE (PCTPMO) AS THE LEAD IMPLEMENTING AGENCY. — The Pasay City Traffic and Parking Management Office is hereby mandated to implement this Ordinance in coordination with all barangay officials who are hereby deputized to effectively implement the provisions of the Ordinance. SECTION 8. PROCEDURE. —- Any person or individual who has violated any of the prohibited acts provided in this ordinance shall be issued a citation ticket cause to be printed by the Office of the City Treasurer of the City government by the employees of the Pasay City Traffic and Parking Management Office (PCTPMO) or barangay officials properly deputized. The Pasay City Traffic and Parking Management Office (PCTPMO)shall be responsible in monitoring the record of conviction of the offender to determine the frequency thereof in case of future violation of the same nature. To this end, the PCTPMO shall be mandated to issue the Order of Payment to the violators upon presentation of the citation ticket before he/she can pay the fine to the Office of the City Treasury. Upon payment, a copy of the receipt shall be given to the PCTPMO for the proper closure/disposal of the charge. SECTION 8. SEPERABILITY CLAUSE. -— If for any reason any section or provision of this Ordinance is declared unconstitutional, other provisions hereof which are not effected thereby shall continue to be in full force and effect. SECTION 9. REPEALING CLAUSE. — Any laws, rules and regulations which are inconsistence with or contrary to the provisions of this Ordinance are hereby amended or repealed. SECTION 10. EFFECTIVITY CLAUSE. — This Ordinance shall take effect immediately. ae . ' \ & 4 aa | \ Page 40f 4 , > ‘Ordinance No. 60 51 , Series of 2019. AN ORDINANCE ADOPTING THE “CHILDREN’S SAFETY ON MOTORCYCLES ACT OF 2015” AND THEREBY PROHIBITING THE RIDING OR TRANSPORTING OF SMALL CHILDREN ON MOTORCYCLES AND TRICYCLES IN FRONT OR AT THE BACK OF THE DRIVER’S SEAT ALONG HIGHWAYS AND is ; PUBLIC ROADS WITHIN THE CITY OF PASAY. Letvcn satan nnecn ones ne ateawwenwnonuwanamenn wes aie ENACTED in the City of Pasay, Metro Manila, Philippines, this 7th day of October 2019. CERTIFIED AND APPROVED BY THE SANG IANG PANLUNGSOD District - I District - Il on. MARK ANTHONY A. CALIXTO City Councilor- agti esiding Officer Hon. MARY GRACE B. SANTOS City Cou Hon. . ANTONIA C. CUNETA City Councilor (On Leave) Hon. ABRAHAM ALBERT Q. ALVINA City Councilor —_—_——__ Hon. MARLON A. PESEBRE City City Councijor City Councilor City Councilor Ex-Officio Members Hon. JULIE G. GONZALES Hon. JOSE MIGUEL A. MANEZ President President Liga Ng Mga Barangay SK Federation Pasay City Chapter Pasay City Chapter Attested by: (On Leave) Hon. NOEL L. DEL ROSARIO City Vice-Mayor & Presiding Officer Approved by¢ | Ce Hon. ee ee City Mayor \ oo | D132: Pasay | E132: 0.47402597 | F132: 56.7826
A133: 6050 | B133: AN ORDINANCE ADOPTING THE NEW EARLY CHILDHOOD CARE AND DEVELOPMENT AND CONVERTING DAY CARE SERVICES TO PASAY CITY EARLY CHILDHOOD CARE DEVELOPMENT PROGRAM (PCECCDP) | C133: -. _, Republic of the Philippines OFFICE OF THE SANGGUNIANG PANLUNGSOD Pasay City, Metro Manila ORDINANCE NO. 6050 , SERIES OF 2019 AN ORDINANCE ADOPTING THE NEW EARLY CIDLDHOOD CARE AND DEVELOPMENT AND CONVERTING DAY CARE SERVICES TO PASAY CITY EARLY CHILDHOOD CARE DEVELOPMENT PROGRAM (PCECCDP) Introduced by: Vice Mayor Noel L. Del Rosario Sponsored by: Councilors Mark Anthony A. Calixto, Mary Grace B. Santos, Ma. Antonia C. Cuneta, Abraham Albert Q. Alvina, Marlon A. Pesebre, Ricardo E. Santos, Allan T. Panaligan, Donnabel M. Vendivel, Amel Regino T. Arceo, Jose C. Isidro, Jr., Editha Y. Manguerra, Aileen C. Padua, Julie G. Gonzales and Jose Miguel A. Maiiez WHEREAS, Section 2(4), Article XIV of the 1987 Philippine Constitution provides that "The State shall encourage non-formal, informal, and indigenous learning systems, as well as self­ /earning, independent, and out of school study programs particularly those that respond to the community needs"; WHEREAS, Section 2 of Republic Act No. 10410, entitled "An Act Recognizing the Age from Zero (0) to Eight (8) as the First Crucial Stage of Educational Development and Strengthening the Early Childhood Care and Development System, Appropriating Funds Therefore And For Other Purposes" also known as the "Early Years Act (EYA) of 2013", states that the State recognizes the age from zero (0) to eight (8) years as the first crucial stage of educational development of which the age from zero (0) to four (4) years shall be the responsibility of the Early Childhood Care and Development (ECCD) Council; WHEREAS, Section 2 of Republic Act No. 8980, also known as the "Early Childhood Care and Development (ECCD) Act" declares that it is the policy of the State to promote the rights of children to survival, development, and special protection; WHEREAS, Republic Act No. 6972 entitled "Barangay-Level Total Development and protection of Children Act", declares that Filipino children up to Six ( 6) years of age deserve the best care and attention at the family and community levels. Towards this end, there is hereby established a day care center in every Barangay with a total development protection of children as provided for by the said Act instituted in every barangay day care center; WHEREAS, Section 6, paragraph (b) of Republic Act No. 6972 mandates the City concerned to provide financial assistance for the establishment of every barangay day care centers ion their locality; WHEREAS, City Ordinance No. 5809, Series of 2017, otherwise known as the Updated Local Code for Children declares that the City of Pasay recognizes the vital role of the youth in nation­ building and shall promote and protect their physical, moral, spiritual, intellectual, and social well-being and that it shall inculcate in the youth patriotism and nationalism, and encourage their involvement in publi j ' 't I • · 6050 · ' Page 2: Ordinanc e No.-- ~ Series of2019. "AN ORDINANCE ADOPTING THE NEW EARLY CHILDHOOD CARE AND DEVELOPMENT AND .., 'CONVERTING DAY CARE SERVICES TO PASAY CITY EARLY CHILDHOOD CARE DEVELOPMENT PROGRAM (PCECCDP) " x------------x WHEREAS, this ordinance seeks to adhere to0 the requirement of the National Government to adopt a Nationalize System for Early Childhood Care and Development (ECCD) relative to the endeavor to establish a National Child Development that is comprehensi ve, integrative and sustainable , that involves multi-sectoral and interagency collaboration at the national and local levels among government; among service providers , families and communities, and among the public and private sectors, nongovernment organizations; professional associations and academic institutions; NOW THEREFORE, BE IT ORDAINED, AS IT IS HEREBY ORDAINED, by the Sangguniang Panlungsod of Pasay, in session assembled that: Section 1. Title. -This ordinance shall be known as "ORDINANCE ADOPTING THE NEW EARLY CHIDLHOOD CARE AND DEVELOPEMT AND CONVERTING DA CARE SERVICES TO QUALITY EARLY CHILDHOOD CARE DEVELOPMENT." Section 2. Scope and Coverage. -This ordinance mandates the adopting and implementation of the New Early Childhood Care Development System under R.A. 10410 within the territorial jurisdiction of Pasay City. Section 3. Definition of Terms. -The following terms are defined in R.A. 10410, as follows: SEC. 4. Definitions. -The following terms are def~ned as follows: (a) Early Childhood Care and Development (ECCD) System shall refer to the full range of health, nutrition, early education and social services development programs that provide for the basic holistic needs of young children from age zero (0) to four (4) years; and to promote their optimum growth and development. These programs shall include: (1) Center-based programs , such as the day care service established under Republic Act No. 6972, otherwise known as the "Barangay -Level Total Development and Protection of Children Act", and hereinafter referred to as the child development service, community or church-based early childhood education programs initiated by nongovernment organizations or people's organizations, workplace-related child care and education programs , child-minding centers, health centers and stations; and (2) Home-based programs, such as the neighborhood-based play groups, family child care programs, parent education and home visiting programs. (b) ECCD Service Providers shall include the various professionals , paraprofessionals and volunteer caregivers who are directly responsible for the care and education of young children from age zero (0) to four (4) years through the various centers and home-based programs. They shall include, but shall not be limited to, day care workers hereinafter referred to as child development workers, child development teachers, teacher- aides, rural health midwives, social workers, community health workers, barangay nutrition scholars, parent effectiveness service volunteers , and family da 'e providers . ' 6050 · ' Page 3: Ordinance No. __ _, Series of 2019. "AN ORDINANCE ADOPTING THE NEW EARLY CHILDHOOD CARE AND DEVELOPMENT AND -t:ONVERTING DAY CARE SERVICES TO PASAY CITY EARLY CHILDHOOD CARE DEVELOPMENT PROGRAM (PCECCDP) " X'---------------, X (c) ECCD Curriculum shall refer to the developmentally-appropriate educational objectives and practices, programs of activities, organized learning experiences , recommended learning materials and appropriate assessment for children from age zero (0) to four (4) years that are implemented by service providers through center and home-based programs. It shall consist of national program goals and guidelines , instructional objectives , and content outlines that are age-appropriate , individually appropriate and culturally relevant. ( d) Parent Education shall refer to the various formal and alternative means of providing parents with information , skills, and support systems to assist them in their roles as their children's primary caregivers and educators. These include public and private parent education programs linked to center, home and media-based child care and education programs. Section 4. Compliance. -The ECCD system shall comply with the National Early Childhood Care Development Program to be implemen ted with the national standards as R.A. 10410 provides that: SEC. 5. System Framework and Components. -The ECCD System shall ensure that the National ECCD Program is implemented in accordance with quality standards for accreditation and for this purpose there shall be established a National ECCD Monitoring and Evaluation Framework . The ECCD System shall include the following components : (a) ECCD Curriculum. -The curriculum shall focus on children's total development and take into account age, individual and socio-cultural appropriateness . It shall promote the delivery of complementary and integrative services for health, nutrition, early childhood education , sanitation and cultural activities. It shall use the child's first language as the medium of instruction; (b) Parent Education and Involvement , Advocacy and Mobilization of Communities . -This component shall harness and develop parents' strengths as providers of ECCD programs at home, as active partners of other stakeholders , as advocates for community concerns that affect children, and as pillars of support for local and national ECCD programs through community organization efforts; (c) Human Resource Development Program. -The program shall establish mechanisms for the systematic professionalization of ECCD service providers through enrolment in educational program in site-based or distance education modes , through pre-service or in-service training including continuing education programs , whereby a registration and credential system shall be developed in the ECCD System; and (d) ECCD Management. -This component shall consist of a continuing process of planning, implementation , supervision , financial management , monitoring , evaluation and reporting to persons concerned and shall encourage the active involvement of and build the capabilities of service providers, parents and local government officials to sustain the program. Section 5. Implemen ting Mechanis m. -The City Government of Pasay, through the Pasay City Social Welfar and Development Department (PSWDD), shall adhere and actively "'"'*&;,,., in coordi ation with the ECCD Council as: ·. Page 4: Ordinance No. 6050 Series of 20~9. ~AN ORDINANCE ADOPTING THE NEW EARLY CHILDHOOD CARE AND DEVELOPMENT AND -'CONVERTING DAY CARE SERVICES TO PASAY CITY EARLY CHILDHOOD CARE DEVELOPMENT PROGRAM ( PCECCDP)" x------------~ x SEC. 7. Implementing Arrangements and Operational Structures . -The implementation of the National ECCD System shall be the responsibility of the ECCD Council. (a) Responsibilities of the ECCD Council. -The ECCD Council shall he responsible for establishing national standards, developing policies and programs , ensuring compliance thereof providing technical assistance and support to the ECCD service providers in consultation with coordinating committees at the provincial, city, municipal and barangay levels. The Department of Education (DepED), the Department of Social Welfare and Development (DSWD), the Department of Health (DOH), the National Nutrition Council (NNC) and the Union of Local Authorities of the Philippines (HEAP) shall meet in an annual workshop to prepare work and financial plans that will coordinate their technical assistance and support for the National ECCD Program. They shall observe existing implementing guidelines that ensure consistency in integrated service delivery within the National ECCD System, as follows: ( 1) The DepED shall recognize the National ECCD Program as the foundation of the learning continuum and shall promote it for all children from age zero (0) to four (4) years; and (2) The DepED, the DSWD, the DOH and the NNC shall provide continuing professional development program support, supplementary learning materials, reference materials, supplemental nutrition and health care services. (b) Responsibilities of Local Government Units. -Local government units (LGUs) shall include a/locations from their Special Education Fund (SEF) and Gender and Development (GAD) Fund in addition to other local funds to be utilized for the following purposes: (1) Support the implementation of their ECCD Program; (2) Organize and support parent cooperatives to establish community­ based ECCD programs; (3) Provide counterpart funds for the continuing professional development of their ECCD public service providers ; and ( 4) Provide the facilities for the conduct of their ECCD Program. (c) Responsibilities of Families and Communities . Families and communities shall support the local ECCD programs by participating in various community-based projects such as, but not limited to, health, nutrition, social development and early childhood education projects for the overall development of their children from age zero (0) to four (4) years. Section 6. Conversion. -It is hereby mandated that there be a conversion of the existing Day Care Centers into Child Development Centers in compliance with R.A. 10410. Moreover, all existing Child Development Centers located in different barangays within the City shall accommoda te children ~~.g in adjacent barangays where no Child Development Centers are established pursuant to 33 of Or inance No. 5809, Series of 2017, othe ·se known as the Updated Local Cod dren. ~ 1 (fJJ(J \ ,Pa,ge 5: Ordinance No. "AN ORDINANCE ADOPTING THE NEW EARLY CHILDHOOD CARE AND DEVELOPMENT AND .-' CONVERTING DAY CARE SERVICES TO PASAY CITY EARLY CHILDHOOD CARE DEVELOPME NT PROGRAM (PCECCDP) " x:-------------x Section 7. Pasay City Early Childhood Care Development Program Technical Working Group. -The Technical Working Group of the Pasay City Early Childhood Care Development Program shall be composed of the same members as the Pasay City Local Council for the Protection of Children as provided for in Section 64 of Ordinance No. 5809, Series of 2017, otherwise known as the Updated Local Code for Children. The Technical Working Group may coordinate with other Local Department and National Agencies when necessary. Section 7.1. Pasay City Social Welfare and Development Department (PSWDD) as the Implementing Office. -Being the office equipped with the data, technical matters and expertise with regard to this matter, the PSWDD shall be the lead agency and the lead implementing office. The members shall determine the benefits to be distributed to each Child Development Center after proper inventory and evaluation. They shall also resolve the manner and the timeliness on how the benefits shall be delivered to the identified beneficiaries. Section 8. Other Provisions. -All other sections and provisions of R.A.10410, otherwise known as "Early Years Act (EY A) of 2013" applicable and necessary for the implementation of the National System for Early Childhood care and Development is hereby adopted as an integral part of this ordinance. Section 9. Appropriations. -The Local Government of Pasay City shall appropriate _.J funds from the Gender and Development (GAD) and Special Education Fund (SEF), in addition M to other Local Funds to be utilized as provided for under Rule VIII, Section 7 of the ~ Implementing Rules and Regulations of Republic Act No. 10410 otherwise known as "Early I Years Act (EYA) of 2013" for the following purposes: (1) Support the implementation of their ECCD Program; (2) Organize and support parent cooperatives to establish community -based ECCD programs; (3) Provide counterpart funds for the continuing professional development of their ECCD public service providers; and ( 4) Provide the facilities for the conduct of their ECCD Program. The Local Government of Pasay City may likewise appropriate funds from its Annual or Supplemental Budget to provide additional support to ECCD programs in its locality subject to all necessary legal, budgetary, accounting and auditing procedures . The City Government, through the PSWDD may also generate funds from inter-governmental donors and government financial institutions to support the programs . Section 10. Repealing Clause. -All ordinances, resolutions, local executive orders, rules and regulations or any part thereof inconsistent herewith are hereby deemed repealed, modified or amended accordingly . Section 11. Separability Clause. -In case any provision of this Ordinance is declared unconstitutional or invalid, the other provisions hereof which are not affected thereby shall continue to be in full force and effect. vity Clause. -This Ordinance shall take effect immediately upon its approval. 1 ¼ Page 6: Ordinance No. 6050 S~ries of 201~. 7 • "AN ORDINANCE ADOPTING THE NEW EARLY CffiLDHOOD CARE AND DEVELOPMENT AND _CONVERTING DAY CARE SERVICES TO PASAY CITY EARLY CHILDHOOD CARE DEVELOPMENT PROGRAM (PCECCDP)" x-------------~x ENACTED in the City of Pasay, Metro Manila, Philippines this day of -----7th Octelter in the Year of Our Lord, Two Thousand Nineteen. on. MARK,~J;;k1}t· CALIXTO City Cooncilodf"'/ff Presiciing Officer Hon. MARY CE B. SANTOS City Council City Councilor (On Leave) Hon. ABRAHAM ALBERT Q. ALVINA City Councilor ~----- Hon. MARLON A. PESEBRE CityCo1or Hon. t~TOS City c1!fncilor Honm~ President Liga ng mga Barangay Pasay Chapter Attested by: (On Leave) Hon. NOELL. DEL ROSARIO City Vice Mayor & Presiding Officer App,oved ~ L--Ex-Officio Members Hon. IMELDA :ALIXTO-RUBIANO City Mayor ct-II H jANALIGAN Ci Hon. DON City Coun · :J City Co Hon. AILEEN C. PADUA City Councilor ~ Hon. JOSE MIGUEL A. MANEZ President SK Federation Pasay Chapter j | D133: Pasay | E133: 0.47402597 | F133: 56.7826
A134: 605 | B134: AN ORDINANCE AMENDING ORD. NO. 545 S-1996 TO READ AS "ORDINANCE MANDATING THE LICENSE DEPARTMENT OF THE CITY GOVERNMENT OF PASAY TO REQUIRE MALE & FEMALE APPLICANTS SECURING PERMIT OR LICENSE TO WORK AS WAITRESSES, DANCERS AND THE LIKE, TO PRESENT A CERTIFIED TRUE COPY OF THERI BIRTH CERFICATES OR CERTIFIED TRUE COPY OF VOTERS AFFIDAVIT AS A REQUIREMENTS FOR THE ISSUANCE OF THE SAID LICENSE. | C134: - ae. y REPUBLIC OF THE PHILIPPINES SANGGUNIANG PANLUNGSOD PASAY CITY, METRO MANILA AN ORDINANCE AMENDING ORD. NO. 545 S-1996 TO READ AS “ORDINANCE MANDATING THE LICENSE DEPARTMENT OF THE CITY GOVERNMENT OF PASAY TO REQUIRE MALE & FEMALE APPLICANTS SECURING PERMIT OR LICENSE TO WORK AS WAITRESSES, DANCERS AND THE LIKE, TO PRESENT A CERTIFIED TRUE COPY OF THEIR BIRTH CERTIFICATES OR CERTIFIED TRUE COPY OF VOTERS AFFIDAVIT AS A REQUIREMENT FOR THE ISSUANCE OF THE SAID LICENSE. ae WHEREAS, Republic Act No. 7658 is an amendment of Republic Act 7160, ees: known as the “Special Protection of Children Against Child Abuse and loitation and Discrimination Act” further prohibits the employment of children below x ORDINANCE NO. © 5.1996 \ 18 years of age in public and private undertakings; . WHEREAS, this protective legislation was initiated to reduce the incidence of child prostitution that is being proliferated by sexual exploitation of boys and girls between 10-18 years old who are compelled to earn a living or sometimes are victims of illegal vf recruiters or promoters; IN WHEREAS, this incidence of prostitution can be minimized if not totally eradicated by effecting an ordinance that would regulate the issuance of license or permit by way of requiring the presentation of a certified true copy of the applicant’s birth certificate and voters affidavit. NOW THEREFORE, BE IT ORDAINED AS IT IS HEREBY ORDAINED, by the Sangguniang Panlungsod of Pasay in session duly assembled that: Section 1 - Prohibited Act. It shall be unlawful for any employee of the License cy Division of the City Government of Pasay to issue permit or license to work to male and female applicants securing the mentioned permit or license to work as waitresses, dancers and the like, without the presentation of the applicant’s certified true copy of his/her birth certificate and voter’ affidavit. Section 2 - Penalty Provision. Any employee of the License Division who shall / be found guilty of violating this ordinance shall be meted with the corresponding | inistrative penalty: First Offense - Reprimand Second Offense - Suspension for thirty (30) days without pay Third Offense - Dismissal Section 3 - Effectivity. This ordinance shall take effect upon passage and dpproval of the Sangguniang Panlungsod of Pasay, posting this ordinance in three (3)conspicuous places in the city and its publication once in a newspaper of general \. circulation in the city. . ENACTED this ; 418% day of of May. in the Year of Our Lord Nineteen Hundred and Ninety-Six > A page 2 of an ordinance amending Ord. No.§64S-1996 to read as : AN ORDINANCE MANDATING THE LICENSE DEPARTMENT OF THE CITY GOVERNMENT OF PASAY TO REQUIRE MALE & FEMALE APPLICANTS SECURING PERMIT OR LICENSE TO WORK AS WAITRESSES, DANCERS AND THE LIKE, TO PRESENT A CERTIFIED TRUE COPY OF THEIR. BIRTH CERTIFICATES OR CERTIFIED TRUE COPY OF VOTERS AFFIDAVIT AS A REQUIREMENT FOR THE ISSUANCE OF THE SAID LICENSE. APPROVED: ee Yup Ae HON. WENCESLAO B. TRINIDAD Acting City Mayor 1. HON. ANTONINO G.CALIXTO) ~“_AL = 2. HON. EMMANUEL M. IBAY .. uf - Gey 3. HON. JUSTO C. JUSTO Ya 4. HON. ROMULO M. CABRERA ey a 5. HON. REYNALDO O. PADUA 7 6. HON. ROBERTO L. ALVAREZ J. HON. EDITA V. VERGEL DE DIOS 8. HON. ULDARICO C. ARABIA 9. HON. ALBERTO V. PAREDES 10. HON. EDUARDO L ADVINCULA 11. HON. TEODULO R. LORCA JR Se os a \ 12. HON. GENEROSO F. CUNETA /\Y 13. HON. CHLOE D. PROTACIO EEN ATTESTED BY: City Secretary | D134: Pasay | E134: 0.47402597 | F134: 56.7826
